{"frameRate":30,"isGlobal":0,"armature":[{"ik":[],"type":"Armature","bone":[{"name":"root","transform":{}},{"transform":{"y":-15.35,"x":23.66},"name":"bone","parent":"root"},{"transform":{"y":-232.99,"x":-0.74},"name":"bone2","parent":"root"},{"length":30,"transform":{"y":-3.76,"skX":-84.18,"skY":-84.18,"x":-3.6},"parent":"bone2","name":"bone3"},{"length":62,"transform":{"y":7.82,"skX":85.9,"skY":85.9,"x":-12.32},"parent":"bone2","name":"bone13"},{"length":76,"transform":{"y":-2.76,"skX":72.5,"skY":72.5,"x":15.54},"parent":"bone2","name":"bone16"},{"length":18,"transform":{"skX":4.03,"skY":4.03,"x":30.85},"parent":"bone3","name":"bone4"},{"length":89,"transform":{"y":-0.19,"skX":-1.55,"skY":-1.55,"x":77.82},"parent":"bone16","name":"bone17"},{"length":77,"transform":{"skX":2.22,"skY":2.22,"x":62.59},"parent":"bone13","name":"bone14"},{"length":22,"transform":{"y":0.33,"skX":9.9,"skY":9.9,"x":78.13},"parent":"bone14","name":"bone15"},{"length":22,"transform":{"y":0.78,"skX":-3.78,"skY":-3.78,"x":89.94},"parent":"bone17","name":"bone18"},{"length":27,"transform":{"skX":-3.03,"skY":-3.03,"x":18.3},"parent":"bone4","name":"bone5"},{"length":42,"transform":{"skX":-29.75,"skY":-29.75,"x":27.61},"parent":"bone5","name":"bone6"},{"length":74,"transform":{"y":10.27,"skX":139.53,"skY":139.53,"x":30.15},"parent":"bone5","name":"bone25"},{"length":37,"transform":{"y":30.89,"skX":142.26,"skY":142.26,"x":27.7},"parent":"bone5","name":"bone7"},{"length":107,"transform":{"y":-3.69,"skX":169.46,"skY":169.46,"x":15.24},"parent":"bone5","name":"bone22"},{"length":85,"transform":{"y":-12.87,"skX":-156.81,"skY":-156.81,"x":16.46},"parent":"bone5","name":"bone26"},{"length":30,"transform":{"y":-16.25,"skX":-169.28,"skY":-169.28,"x":9.81},"parent":"bone5","name":"bone10"},{"length":93,"transform":{"y":0.16,"skX":-37.65,"skY":-37.65,"x":-0.63},"parent":"bone22","name":"bone23"},{"length":52,"transform":{"skX":3.47,"skY":3.47,"x":30.16},"parent":"bone10","name":"bone11"},{"length":140,"transform":{"y":6.36,"skX":-162.22,"skY":-162.22,"x":27.19},"parent":"bone6","name":"bone19"},{"length":80,"transform":{"y":0.85,"skX":31.72,"skY":31.72,"x":0.42},"parent":"bone22","name":"bone24"},{"length":51,"transform":{"skX":36.07,"skY":36.07,"x":37.69},"parent":"bone7","name":"bone8"},{"length":13,"transform":{"y":-0.44,"skX":7.85,"skY":7.85,"x":53.07},"parent":"bone8","name":"bone9"},{"length":115,"transform":{"y":-5.91,"skX":-36.43,"skY":-36.43,"x":5.94},"parent":"bone19","name":"bone20"},{"length":102,"transform":{"y":7.95,"skX":19.72,"skY":19.72,"x":16.74},"parent":"bone19","name":"bone21"},{"length":22,"transform":{"skX":-4.97,"skY":-4.97,"x":52.35},"parent":"bone11","name":"bone12"}],"aabb":{"width":247,"y":-372.6883129790923,"height":374.3783129790923,"x":-91.74000000000001},"slot":[{"color":{},"name":"Ellipse 2","parent":"bone"},{"z":1,"color":{},"name":"Layer 35","parent":"root"},{"z":2,"color":{},"name":"Layer 36","parent":"root"},{"z":3,"color":{},"name":"Arm Left","parent":"root"},{"z":4,"color":{},"name":"Left Cape","parent":"bone26"},{"z":5,"color":{},"name":"Arm LeftOver","parent":"root","displayIndex":-1},{"z":6,"color":{},"name":"Layer 37","parent":"root"},{"z":7,"color":{},"name":"Arm right","parent":"root"},{"z":8,"color":{},"name":"Right Cape","parent":"bone25"}],"animation":[{"duration":55,"frame":[],"bone":[{"frame":[{"duration":10,"transform":{},"curve":[0.25,0,1,0]},{"duration":5,"transform":{"scX":0.92},"curve":[0.25,0,0.75,1]},{"duration":8,"transform":{"scX":0.82},"curve":[0.25,0,0,1]},{"duration":17,"transform":{"scX":0.74,"x":-37.83},"curve":[0.25,0,0.75,1]},{"duration":15,"transform":{"scX":1.01,"x":-37.83},"curve":[0.25,0,0.75,1]},{"duration":0,"transform":{}}],"name":"bone"},{"frame":[{"duration":10,"transform":{},"curve":[0.25,0,1,0]},{"duration":5,"transform":{"y":7.21,"x":39.83},"curve":[0.25,0,0.75,1]},{"duration":8,"transform":{"y":7.21,"x":55},"curve":[0.25,0,0,1]},{"duration":19,"transform":{"y":-26.54,"x":-30.04},"curve":[0.25,0,0.75,1]},{"duration":13,"transform":{"y":16.29,"x":-13.07},"curve":[0.25,0,0.75,1]},{"duration":0,"transform":{}}],"name":"bone2"},{"frame":[{"duration":10,"transform":{},"tweenEasing":0},{"duration":5,"transform":{},"curve":[0.25,0,0.75,1]},{"duration":8,"transform":{"skX":5.22,"skY":5.22},"curve":[0.25,0,0,1]},{"duration":19,"transform":{"skX":2.63,"skY":2.63}},{"duration":13,"transform":{"skX":2.63,"skY":2.63},"curve":[0.25,0,0.75,1]},{"duration":0,"transform":{}}],"name":"bone3"},{"frame":[{"duration":15,"transform":{},"tweenEasing":0},{"duration":8,"transform":{},"curve":[0.25,0,0,1]},{"duration":19,"transform":{"skX":-8.27,"skY":-8.27},"curve":[0.25,0,0.75,1]},{"duration":13,"transform":{}}],"name":"bone7"},{"frame":[{"duration":10,"transform":{},"curve":[0.25,0,1,0]},{"duration":5,"transform":{"skX":-10.49,"skY":-10.49},"curve":[0.25,0,0.75,1]},{"duration":8,"transform":{"skX":-35.22,"skY":-35.22},"curve":[0.25,0,0,1]},{"duration":19,"transform":{"skX":70.66,"skY":70.66},"curve":[0.25,0,0.75,1]},{"duration":13,"transform":{"skX":60.15,"skY":60.15},"curve":[0.25,0,0.75,1]},{"duration":0,"transform":{}}],"name":"bone10"},{"frame":[{"duration":10,"transform":{},"tweenEasing":0},{"duration":5,"transform":{},"curve":[0.25,0,0.75,1]},{"duration":8,"transform":{"skX":64.04,"skY":64.04},"curve":[0.25,0,0,1]},{"duration":19,"transform":{"skX":-0.39,"skY":-0.39}},{"duration":13,"transform":{"skX":-0.39,"skY":-0.39},"curve":[0.25,0,0.75,1]},{"duration":0,"transform":{}}],"name":"bone11"},{"frame":[{"duration":15,"transform":{},"tweenEasing":0},{"duration":8,"transform":{},"curve":[0.25,0,0,1]},{"duration":19,"transform":{"skX":19.39,"skY":19.39},"curve":[0.25,0,0.75,1]},{"duration":13,"transform":{"skX":-9.67,"skY":-9.67},"curve":[0.25,0,0.75,1]},{"duration":0,"transform":{}}],"name":"bone12"},{"frame":[{"duration":10,"transform":{},"curve":[0.25,0,1,0]},{"duration":5,"transform":{"skX":9.52,"skY":9.52}},{"duration":8,"transform":{"skX":9.52,"skY":9.52},"curve":[0.25,0,0,1]},{"duration":19,"transform":{"skX":4.8,"skY":4.8},"curve":[0.25,0,0.75,1]},{"duration":13,"transform":{"skX":1.65,"skY":1.65},"curve":[0.25,0,0.75,1]},{"duration":0,"transform":{}}],"name":"bone13"},{"frame":[{"duration":10,"transform":{},"curve":[0.25,0,1,0]},{"duration":5,"transform":{"skX":-15.36,"skY":-15.36}},{"duration":8,"transform":{"skX":-15.36,"skY":-15.36},"curve":[0.25,0,0,1]},{"duration":19,"transform":{"skX":-7.75,"skY":-7.75}},{"duration":13,"transform":{"skX":-7.75,"skY":-7.75},"curve":[0.25,0,0.75,1]},{"duration":0,"transform":{}}],"name":"bone14"},{"frame":[{"duration":10,"transform":{},"curve":[0.25,0,1,0]},{"duration":5,"transform":{"skX":15.69,"skY":15.69}},{"duration":8,"transform":{"skX":15.69,"skY":15.69},"curve":[0.25,0,0,1]},{"duration":19,"transform":{"skX":7.91,"skY":7.91},"curve":[0.25,0,0.75,1]},{"duration":13,"transform":{"skX":13.37,"skY":13.37},"curve":[0.25,0,0.75,1]},{"duration":0,"transform":{}}],"name":"bone16"},{"frame":[{"duration":15,"transform":{},"tweenEasing":0},{"duration":8,"transform":{},"curve":[0.25,0,0,1]},{"duration":19,"transform":{"skX":-22.12,"skY":-22.12},"curve":[0.25,0,0.75,1]},{"duration":13,"transform":{"skX":6.57,"skY":6.57},"curve":[0.25,0,0.75,1]},{"duration":0,"transform":{}}],"name":"bone20"},{"frame":[{"duration":15,"transform":{},"tweenEasing":0},{"duration":8,"transform":{},"curve":[0.25,0,0,1]},{"duration":19,"transform":{"skX":33.94,"skY":33.94},"curve":[0.25,0,0.75,1]},{"duration":13,"transform":{"skX":-1.06,"skY":-1.06},"curve":[0.25,0,0.75,1]},{"duration":0,"transform":{}}],"name":"bone21"},{"frame":[{"duration":15,"transform":{},"tweenEasing":0},{"duration":8,"transform":{},"curve":[0.25,0,0,1]},{"duration":19,"transform":{"skX":-54.83,"skY":-54.83},"curve":[0.25,0,0.75,1]},{"duration":13,"transform":{"skX":-21.44,"skY":-21.44},"curve":[0.25,0,0.75,1]},{"duration":0,"transform":{}}],"name":"bone23"},{"frame":[{"duration":10,"transform":{},"tweenEasing":0},{"duration":5,"transform":{},"curve":[0.25,0,0.75,1]},{"duration":8,"transform":{"skX":-11.83,"skY":-11.83},"curve":[0.25,0,0,1]},{"duration":19,"transform":{"skX":40.42,"skY":40.42},"curve":[0.25,0,0.75,1]},{"duration":13,"transform":{"skX":3.81,"skY":3.81},"curve":[0.25,0,0.75,1]},{"duration":0,"transform":{}}],"name":"bone24"},{"frame":[{"duration":10,"transform":{},"curve":[0.25,0,1,0]},{"duration":5,"transform":{"skX":-18.49,"skY":-18.49},"curve":[0.25,0,0.75,1]},{"duration":8,"transform":{"skX":-6.29,"skY":-6.29},"curve":[0.25,0,0,1]},{"duration":19,"transform":{"skX":-71.15,"skY":-71.15},"curve":[0.25,0,0.75,1]},{"duration":13,"transform":{"skX":-8.45,"skY":-8.45},"curve":[0.25,0,0.75,1]},{"duration":0,"transform":{}}],"name":"bone25"},{"frame":[{"duration":10,"transform":{},"tweenEasing":0},{"duration":5,"transform":{},"curve":[0.25,0,0.75,1]},{"duration":8,"transform":{"skX":-19.08,"skY":-19.08},"curve":[0.25,0,0,1]},{"duration":19,"transform":{"skX":38.2,"skY":38.2},"curve":[0.25,0,0.75,1]},{"duration":13,"transform":{"skX":0.94,"skY":0.94},"curve":[0.25,0,0.75,1]},{"duration":0,"transform":{}}],"name":"bone26"},{"frame":[{"duration":55,"transform":{}}],"name":"root"},{"frame":[{"duration":55,"transform":{}}],"name":"bone4"},{"frame":[{"duration":55,"transform":{}}],"name":"bone17"},{"frame":[{"duration":55,"transform":{}}],"name":"bone5"},{"frame":[{"duration":55,"transform":{}}],"name":"bone18"},{"frame":[{"duration":55,"transform":{}}],"name":"bone15"},{"frame":[{"duration":55,"transform":{}}],"name":"bone6"},{"frame":[{"duration":55,"transform":{}}],"name":"bone22"},{"frame":[{"duration":55,"transform":{}}],"name":"bone8"},{"frame":[{"duration":55,"transform":{}}],"name":"bone19"},{"frame":[{"duration":55,"transform":{}}],"name":"bone9"}],"slot":[{"frame":[{"tweenEasing":null,"duration":55,"displayIndex":-1}],"name":"Arm Left"},{"frame":[{"tweenEasing":null,"duration":55}],"name":"Arm LeftOver"}],"ffd":[],"ik":[],"name":"Attack A"},{"duration":69,"frame":[],"bone":[{"frame":[{"duration":10,"transform":{},"curve":[0.25,0,1,0]},{"duration":5,"transform":{"scX":0.92},"curve":[0.25,0,0.75,1]},{"duration":5,"transform":{"scX":0.82},"curve":[0.25,0,0,1]},{"duration":22,"transform":{"scX":0.74,"x":-37.83}},{"duration":12,"transform":{"scX":0.74,"x":-37.83},"curve":[0.25,0,0.75,1]},{"duration":15,"transform":{"scX":1.01,"x":-37.83},"curve":[0.25,0,0.75,1]},{"duration":0,"transform":{}}],"name":"bone"},{"frame":[{"duration":10,"transform":{},"curve":[0.25,0,1,0]},{"duration":5,"transform":{"y":7.21,"x":39.83},"curve":[0.25,0,0.75,1]},{"duration":5,"transform":{"y":7.21,"x":55},"curve":[0.25,0,0,1]},{"duration":22,"transform":{"y":-17.12,"x":-13.07},"curve":[0.25,0,0.75,1]},{"duration":14,"transform":{"y":-17.12,"x":-5.76},"curve":[0.25,0,0.75,1]},{"duration":13,"transform":{"y":16.29,"x":-13.07},"curve":[0.25,0,0.75,1]},{"duration":0,"transform":{}}],"name":"bone2"},{"frame":[{"duration":10,"transform":{},"tweenEasing":0},{"duration":5,"transform":{},"curve":[0.25,0,0.75,1]},{"duration":5,"transform":{"skX":5.22,"skY":5.22},"curve":[0.25,0,0,1]},{"duration":22,"transform":{"skX":2.63,"skY":2.63},"curve":[0.25,0,0.75,1]},{"duration":14,"transform":{"skX":6.04,"skY":6.04},"curve":[0.25,0,0.75,1]},{"duration":13,"transform":{"skX":2.63,"skY":2.63},"curve":[0.25,0,0.75,1]},{"duration":0,"transform":{}}],"name":"bone3"},{"frame":[{"duration":20,"transform":{},"tweenEasing":0},{"duration":22,"transform":{},"curve":[0.25,0,0.75,1]},{"duration":14,"transform":{"skX":-3.01,"skY":-3.01},"curve":[0.25,0,0.75,1]},{"duration":13,"transform":{}}],"name":"bone4"},{"frame":[{"duration":15,"transform":{},"tweenEasing":0},{"duration":5,"transform":{},"curve":[0.25,0,0,1]},{"duration":22,"transform":{"y":-5.15,"x":-1.14},"curve":[0.375,0.5,0.75,1]},{"duration":14,"transform":{"y":-0.48,"x":-0.11},"curve":[0.375,0.5,0.75,1]},{"duration":13,"transform":{}}],"name":"bone5"},{"frame":[{"duration":10,"transform":{},"curve":[0.25,0,1,0]},{"duration":5,"transform":{"skX":-10.49,"skY":-10.49},"curve":[0.25,0,0.75,1]},{"duration":5,"transform":{"skX":-35.22,"skY":-35.22},"curve":[0.25,0,0,1]},{"duration":22,"transform":{"skX":70.66,"skY":70.66}},{"duration":14,"transform":{"skX":70.66,"skY":70.66},"curve":[0.25,0,0.75,1]},{"duration":13,"transform":{"skX":-3.51,"skY":-3.51},"curve":[0.25,0,0.75,1]},{"duration":0,"transform":{}}],"name":"bone10"},{"frame":[{"duration":10,"transform":{},"tweenEasing":0},{"duration":5,"transform":{},"curve":[0.25,0,0.75,1]},{"duration":5,"transform":{"skX":64.04,"skY":64.04},"curve":[0.25,0,0,1]},{"duration":36,"transform":{"skX":-0.39,"skY":-0.39}},{"duration":13,"transform":{"skX":-0.39,"skY":-0.39},"curve":[0.25,0,0.75,1]},{"duration":0,"transform":{}}],"name":"bone11"},{"frame":[{"duration":15,"transform":{},"tweenEasing":0},{"duration":5,"transform":{},"curve":[0.25,0,0,1]},{"duration":36,"transform":{"skX":-9.67,"skY":-9.67}},{"duration":13,"transform":{"skX":-9.67,"skY":-9.67},"curve":[0.25,0,0.75,1]},{"duration":0,"transform":{}}],"name":"bone12"},{"frame":[{"duration":10,"transform":{},"curve":[0.25,0,1,0]},{"duration":5,"transform":{"skX":9.52,"skY":9.52}},{"duration":5,"transform":{"skX":9.52,"skY":9.52},"curve":[0.25,0,0,1]},{"duration":22,"transform":{"skX":4.8,"skY":4.8},"curve":[0.25,0,0.75,1]},{"duration":14,"transform":{"skX":8.83,"skY":8.83},"curve":[0.25,0,0.75,1]},{"duration":13,"transform":{"skX":1.65,"skY":1.65},"curve":[0.25,0,0.75,1]},{"duration":0,"transform":{}}],"name":"bone13"},{"frame":[{"duration":10,"transform":{},"curve":[0.25,0,1,0]},{"duration":5,"transform":{"skX":-15.36,"skY":-15.36}},{"duration":5,"transform":{"skX":-15.36,"skY":-15.36},"curve":[0.25,0,0,1]},{"duration":22,"transform":{"skX":-7.75,"skY":-7.75},"curve":[0.25,0,0.75,1]},{"duration":14,"transform":{"skX":-12.22,"skY":-12.22},"curve":[0.25,0,0.75,1]},{"duration":13,"transform":{"skX":-7.75,"skY":-7.75},"curve":[0.25,0,0.75,1]},{"duration":0,"transform":{}}],"name":"bone14"},{"frame":[{"duration":10,"transform":{},"curve":[0.25,0,1,0]},{"duration":5,"transform":{"skX":15.69,"skY":15.69}},{"duration":5,"transform":{"skX":15.69,"skY":15.69},"curve":[0.25,0,0,1]},{"duration":22,"transform":{"skX":7.91,"skY":7.91}},{"duration":14,"transform":{"skX":7.91,"skY":7.91},"curve":[0.25,0,0.75,1]},{"duration":13,"transform":{"skX":13.37,"skY":13.37},"curve":[0.25,0,0.75,1]},{"duration":0,"transform":{}}],"name":"bone16"},{"frame":[{"duration":20,"transform":{},"tweenEasing":0},{"duration":22,"transform":{},"curve":[0.25,0,0.75,1]},{"duration":14,"transform":{"skX":-14.77,"skY":-14.77},"curve":[0.25,0,0.75,1]},{"duration":13,"transform":{}}],"name":"bone19"},{"frame":[{"duration":19,"transform":{},"tweenEasing":0},{"duration":19,"transform":{},"curve":[0.25,0,0,1]},{"duration":18,"transform":{"skX":-13.55,"skY":-13.55},"curve":[0.705,0,0.747,1]},{"duration":13,"transform":{"skX":6.57,"skY":6.57},"curve":[0.25,0,0.75,1]},{"duration":0,"transform":{}}],"name":"bone20"},{"frame":[{"duration":15,"transform":{},"tweenEasing":0},{"duration":5,"transform":{},"curve":[0.25,0,0,1]},{"duration":22,"transform":{"skX":25.26,"skY":25.26}},{"duration":14,"transform":{"skX":25.26,"skY":25.26},"curve":[0.25,0,0.75,1]},{"duration":13,"transform":{"skX":-1.06,"skY":-1.06},"curve":[0.25,0,0.75,1]},{"duration":0,"transform":{}}],"name":"bone21"},{"frame":[{"duration":15,"transform":{},"tweenEasing":0},{"duration":5,"transform":{},"curve":[0.25,0,0,1]},{"duration":3,"transform":{"skX":-54.83,"skY":-54.83},"curve":[0.297,0,0.634,0.37]},{"duration":9,"transform":{"skX":-42.85,"skY":-42.85},"curve":[0.29,0.19,0.649,0.61]},{"duration":7,"transform":{"skX":-60.6,"skY":-60.6},"curve":[0.356,0.41,0.706,0.8]},{"duration":3,"transform":{"skX":-38.24,"skY":-38.24},"curve":[0.366,0.63,0.703,1]},{"duration":14,"transform":{"skX":-54.83,"skY":-54.83},"curve":[0.243,0,0.689,0.75]},{"duration":13,"transform":{"skX":-21.44,"skY":-21.44},"curve":[0.25,0,0.75,1]},{"duration":0,"transform":{}}],"name":"bone23"},{"frame":[{"duration":10,"transform":{},"tweenEasing":0},{"duration":5,"transform":{},"curve":[0.25,0,0.75,1]},{"duration":5,"transform":{"skX":-11.83,"skY":-11.83},"curve":[0.25,0,0,1]},{"duration":15,"transform":{"skX":33.29,"skY":33.29},"curve":[0.243,0,0.652,0.61]},{"duration":7,"transform":{"skX":31.33,"skY":31.33},"curve":[0.382,0.58,0.733,1]},{"duration":14,"transform":{"skX":20.38,"skY":20.38},"curve":[0.25,0,0.75,1]},{"duration":13,"transform":{"skX":3.81,"skY":3.81},"curve":[0.25,0,0.75,1]},{"duration":0,"transform":{}}],"name":"bone24"},{"frame":[{"duration":10,"transform":{},"curve":[0.25,0,1,0]},{"duration":5,"transform":{"skX":-18.49,"skY":-18.49},"curve":[0.25,0,0.75,1]},{"duration":5,"transform":{"skX":-6.29,"skY":-6.29},"curve":[0.25,0,0,1]},{"duration":3,"transform":{"skX":-56.45,"skY":-56.45},"curve":[0.283,0,0.625,0.39]},{"duration":5,"transform":{"skX":-40.32,"skY":-40.32},"curve":[0.305,0.24,0.656,0.63]},{"duration":9,"transform":{"skX":-65.44,"skY":-65.44},"curve":[0.361,0.43,0.714,0.84]},{"duration":5,"transform":{"skX":-40.11,"skY":-40.11},"curve":[0.361,0.64,0.696,1]},{"duration":14,"transform":{"skX":-56.45,"skY":-56.45},"curve":[0.25,0,0.75,1]},{"duration":13,"transform":{"skX":-8.45,"skY":-8.45},"curve":[0.25,0,0.75,1]},{"duration":0,"transform":{}}],"name":"bone25"},{"frame":[{"duration":10,"transform":{},"tweenEasing":0},{"duration":5,"transform":{},"curve":[0.25,0,0.75,1]},{"duration":5,"transform":{"skX":-19.08,"skY":-19.08},"curve":[0.25,0,0,1]},{"duration":6,"transform":{"skX":23.93,"skY":23.93},"curve":[0.273,0,0.619,0.41]},{"duration":9,"transform":{"skX":14.38,"skY":14.38},"curve":[0.316,0.28,0.675,0.69]},{"duration":7,"transform":{"skX":31.93,"skY":31.93},"curve":[0.382,0.58,0.733,1]},{"duration":14,"transform":{"skX":23.93,"skY":23.93},"curve":[0.25,0,0.75,1]},{"duration":13,"transform":{"skX":0.94,"skY":0.94},"curve":[0.25,0,0.75,1]},{"duration":0,"transform":{}}],"name":"bone26"},{"frame":[{"duration":69,"transform":{}}],"name":"root"},{"frame":[{"duration":69,"transform":{}}],"name":"bone17"},{"frame":[{"duration":69,"transform":{}}],"name":"bone18"},{"frame":[{"duration":69,"transform":{}}],"name":"bone15"},{"frame":[{"duration":69,"transform":{}}],"name":"bone6"},{"frame":[{"duration":69,"transform":{}}],"name":"bone7"},{"frame":[{"duration":69,"transform":{}}],"name":"bone22"},{"frame":[{"duration":69,"transform":{}}],"name":"bone8"},{"frame":[{"duration":69,"transform":{}}],"name":"bone9"}],"slot":[{"frame":[{"tweenEasing":null,"duration":69,"displayIndex":-1}],"name":"Arm Left"},{"frame":[{"tweenEasing":null,"duration":69}],"name":"Arm LeftOver"}],"ffd":[],"ik":[],"name":"Attack B"},{"duration":48,"frame":[],"bone":[{"frame":[{"duration":10,"transform":{},"curve":[0.263,0,1,0]},{"duration":5,"transform":{"scX":0.88,"x":-35.4},"curve":[0.25,0,0.75,1]},{"duration":9,"transform":{"scX":0.76,"x":-13.86},"curve":[0.25,0,0,1]},{"duration":24,"transform":{"x":-55.44},"curve":[0.125,0,0.875,1]},{"duration":0,"transform":{}}],"name":"bone"},{"frame":[{"duration":10,"transform":{},"curve":[0.25,0,1,0]},{"duration":5,"transform":{"y":15.29,"x":-30.35},"curve":[0.25,0,0.75,1]},{"duration":9,"transform":{"y":15.29,"x":-19.83},"curve":[0.25,0,0,1]},{"duration":24,"transform":{"y":25.99,"x":-28.25},"curve":[0.25,0,0.75,1]},{"duration":0,"transform":{}}],"name":"bone2"},{"frame":[{"duration":10,"transform":{},"tweenEasing":0},{"duration":5,"transform":{},"curve":[0.25,0,0.75,1]},{"duration":9,"transform":{"x":6.27},"curve":[0.25,0,0,1]},{"duration":24,"transform":{"skX":11.06,"skY":11.06},"curve":[0.125,0,0.875,1]},{"duration":0,"transform":{}}],"name":"bone3"},{"frame":[{"duration":10,"transform":{},"tweenEasing":0},{"duration":5,"transform":{},"curve":[0.25,0,0.75,1]},{"duration":9,"transform":{"y":2.34,"x":0.24},"curve":[0.25,0,0,1]},{"duration":24,"transform":{}}],"name":"bone4"},{"frame":[{"duration":10,"transform":{},"tweenEasing":0},{"duration":5,"transform":{},"curve":[0.25,0,0.75,1]},{"duration":9,"transform":{"y":12.47,"x":2.16},"curve":[0.25,0,0,1]},{"duration":24,"transform":{"y":-8.34,"x":-1.45},"curve":[0.25,0,0.75,1]},{"duration":0,"transform":{}}],"name":"bone5"},{"frame":[{"duration":15,"transform":{},"tweenEasing":0},{"duration":9,"transform":{},"curve":[0.25,0,0,1]},{"duration":24,"transform":{"skX":-1.56,"skY":-1.56},"curve":[0.25,0,0.75,1]},{"duration":0,"transform":{}}],"name":"bone6"},{"frame":[{"duration":10,"transform":{},"curve":[0.25,0,1,0]},{"duration":5,"transform":{"y":-11.05,"skX":-23.49,"skY":-23.49,"x":-0.43}},{"duration":9,"transform":{"y":-11.05,"skX":-23.49,"skY":-23.49,"x":-0.43},"curve":[0.25,0,0,1]},{"duration":24,"transform":{"y":-11.05,"skX":-4.83,"skY":-4.83,"x":-0.43},"curve":[0.25,0,0.75,1]},{"duration":0,"transform":{}}],"name":"bone7"},{"frame":[{"duration":10,"transform":{},"curve":[0.25,0,1,0]},{"duration":14,"transform":{"y":5.16,"skX":8.55,"skY":8.55,"x":4.99}},{"duration":24,"transform":{"y":5.16,"skX":8.55,"skY":8.55,"x":4.99},"curve":[0.25,0,0.75,1]},{"duration":0,"transform":{}}],"name":"bone8"},{"frame":[{"duration":10,"transform":{},"curve":[0.25,0,1,0]},{"duration":5,"transform":{"skX":56.53,"skY":56.53},"curve":[0.25,0,0.75,1]},{"duration":9,"transform":{"y":14.08,"skX":48.68,"skY":48.68,"x":9.89},"curve":[0.25,0,0,1]},{"duration":11,"transform":{"y":2.03,"skX":76.32,"skY":76.32,"x":7.95}},{"duration":13,"transform":{"y":2.03,"skX":76.32,"skY":76.32,"x":7.95},"curve":[0.25,0,0.75,1]},{"duration":0,"transform":{}}],"name":"bone10"},{"frame":[{"duration":10,"transform":{},"curve":[0.25,0,1,0]},{"duration":5,"transform":{"skX":15.19,"skY":15.19},"curve":[0.25,0,0.75,1]},{"duration":9,"transform":{"skX":27.31,"skY":27.31},"curve":[0.25,0,0,1]},{"duration":24,"transform":{"skX":22.49,"skY":22.49},"curve":[0.25,0,0.75,1]},{"duration":0,"transform":{}}],"name":"bone11"},{"frame":[{"duration":10,"transform":{},"curve":[0.25,0,1,0]},{"duration":5,"transform":{"skX":-23.7,"skY":-23.7}},{"duration":9,"transform":{"skX":-23.7,"skY":-23.7},"curve":[0.25,0,0,1]},{"duration":24,"transform":{"skX":26.4,"skY":26.4},"curve":[0.25,0,0.75,1]},{"duration":0,"transform":{}}],"name":"bone12"},{"frame":[{"duration":10,"transform":{},"curve":[0.25,0,1,0]},{"duration":5,"transform":{"skX":15.37,"skY":15.37},"curve":[0.25,0,0.75,1]},{"duration":9,"transform":{"skX":5.53,"skY":5.53},"curve":[0.25,0,0,1]},{"duration":24,"transform":{"y":-7.31,"skX":24.87,"skY":24.87,"x":-7.74},"curve":[0.25,0,0.75,1]},{"duration":0,"transform":{}}],"name":"bone13"},{"frame":[{"duration":10,"transform":{},"curve":[0.25,0,1,0]},{"duration":5,"transform":{"skX":-16.65,"skY":-16.65}},{"duration":9,"transform":{"skX":-16.65,"skY":-16.65},"curve":[0.25,0,0,1]},{"duration":24,"transform":{"skX":-22.18,"skY":-22.18},"curve":[0.371,0.48,0.752,1]},{"duration":0,"transform":{}}],"name":"bone14"},{"frame":[{"duration":10,"transform":{},"curve":[0.25,0,1,0]},{"duration":5,"transform":{"skX":9.29,"skY":9.29},"curve":[0.25,0,0.75,1]},{"duration":9,"transform":{"skX":5.92,"skY":5.92,"x":4.51},"curve":[0.25,0,0,1]},{"duration":24,"transform":{"y":-2.58,"skX":10.28,"skY":10.28,"x":-4.73},"curve":[0.25,0,0.75,1]},{"duration":0,"transform":{}}],"name":"bone16"},{"frame":[{"duration":15,"transform":{},"tweenEasing":0},{"duration":9,"transform":{},"curve":[0.25,0,0,1]},{"duration":24,"transform":{"skX":-6.8,"skY":-6.8},"curve":[0.25,0,0.75,1]},{"duration":0,"transform":{}}],"name":"bone17"},{"frame":[{"duration":10,"transform":{},"curve":[0.25,0,1,0]},{"duration":19,"transform":{"skX":8.92,"skY":8.92}},{"duration":19,"transform":{"skX":8.92,"skY":8.92},"curve":[0.25,0,0.75,1]},{"duration":0,"transform":{}}],"name":"bone19"},{"frame":[{"duration":15,"transform":{},"tweenEasing":0},{"duration":9,"transform":{},"curve":[0.25,0,0,1]},{"duration":24,"transform":{"skX":19.56,"skY":19.56},"curve":[0.25,0,0.75,1]},{"duration":0,"transform":{}}],"name":"bone20"},{"frame":[{"duration":15,"transform":{},"tweenEasing":0},{"duration":9,"transform":{},"curve":[0.563,0.05,0.529,1]},{"duration":24,"transform":{"skX":31.18,"skY":31.18},"curve":[0.25,0,0.75,1]},{"duration":0,"transform":{}}],"name":"bone21"},{"frame":[{"duration":10,"transform":{},"curve":[0.25,0,1,0]},{"duration":5,"transform":{"skX":-5.96,"skY":-5.96}},{"duration":9,"transform":{"skX":-5.96,"skY":-5.96},"curve":[0.517,0.02,0.613,0.99]},{"duration":24,"transform":{"skX":15.97,"skY":15.97},"curve":[0.25,0,0.75,1]},{"duration":0,"transform":{}}],"name":"bone22"},{"frame":[{"duration":10,"transform":{},"curve":[0.25,0,1,0]},{"duration":14,"transform":{"skX":-21.84,"skY":-21.84}},{"duration":24,"transform":{"skX":-21.84,"skY":-21.84},"curve":[0.25,0,0.75,1]},{"duration":0,"transform":{}}],"name":"bone23"},{"frame":[{"duration":10,"transform":{},"curve":[0.25,0,1,0]},{"duration":5,"transform":{"skX":7.94,"skY":7.94}},{"duration":9,"transform":{"skX":7.94,"skY":7.94},"curve":[0.25,0,0,1]},{"duration":24,"transform":{"y":-3.05,"skX":24.58,"skY":24.58,"x":-4.18},"curve":[0.25,0,0.75,1]},{"duration":0,"transform":{}}],"name":"bone24"},{"frame":[{"duration":10,"transform":{},"curve":[0.25,0,1,0]},{"duration":5,"transform":{"y":-0.63,"skX":-13.2,"skY":-13.2,"x":5.31}},{"duration":9,"transform":{"y":-0.63,"skX":-13.2,"skY":-13.2,"x":5.31},"curve":[0.25,0,0,1]},{"duration":24,"transform":{"y":-0.63,"skX":16.61,"skY":16.61,"x":5.31},"curve":[0.25,0,0.75,1]},{"duration":0,"transform":{}}],"name":"bone25"},{"frame":[{"duration":10,"transform":{},"curve":[0.25,0,1,0]},{"duration":5,"transform":{"skX":11.36,"skY":11.36}},{"duration":9,"transform":{"skX":11.36,"skY":11.36},"curve":[0.25,0,0,1]},{"duration":24,"transform":{"skX":34.72,"skY":34.72},"curve":[0.25,0,0.75,1]},{"duration":0,"transform":{}}],"name":"bone26"},{"frame":[{"duration":48,"transform":{}}],"name":"root"},{"frame":[{"duration":48,"transform":{}}],"name":"bone18"},{"frame":[{"duration":48,"transform":{}}],"name":"bone15"},{"frame":[{"duration":48,"transform":{}}],"name":"bone9"}],"slot":[{"frame":[{"tweenEasing":null,"duration":48,"displayIndex":-1}],"name":"Arm Left"},{"frame":[{"tweenEasing":null,"duration":48}],"name":"Arm LeftOver"}],"ffd":[],"ik":[],"name":"Attack C"},{"duration":56,"frame":[],"bone":[{"frame":[{"duration":10,"transform":{},"curve":[0.25,0,1,0]},{"duration":5,"transform":{"scX":0.92}},{"duration":5,"transform":{"scX":0.92},"curve":[0.25,0,0,1]},{"duration":3,"transform":{"scX":0.74,"x":-37.83}},{"duration":19,"transform":{"scX":0.74,"x":-37.83},"curve":[0.25,0,0.75,1]},{"duration":14,"transform":{"scX":1.01,"x":-37.83},"curve":[0.25,0,0.75,1]},{"duration":0,"transform":{}}],"name":"bone"},{"frame":[{"duration":10,"transform":{},"curve":[0.125,0,1,0.5]},{"duration":5,"transform":{"y":7.21,"x":39.83},"curve":[0.25,0,0.75,1]},{"duration":5,"transform":{"y":7.21,"x":60.29},"curve":[0.25,0,0,1]},{"duration":3,"transform":{"y":11.1,"skX":-8.4,"skY":-8.4,"x":-73.55}},{"duration":33,"transform":{"y":11.1,"skX":-8.4,"skY":-8.4,"x":-73.55},"curve":[0.25,0,0.75,1]},{"duration":0,"transform":{}}],"name":"bone2"},{"frame":[{"duration":10,"transform":{},"tweenEasing":0},{"duration":5,"transform":{},"curve":[0.25,0,0.75,1]},{"duration":5,"transform":{"x":6.05},"curve":[0.25,0,0,1]},{"duration":3,"transform":{"skX":-8.95,"skY":-8.95},"tweenEasing":0},{"duration":33,"transform":{"skX":-8.95,"skY":-8.95},"curve":[0.25,0,0.75,1]},{"duration":0,"transform":{}}],"name":"bone3"},{"frame":[{"duration":10,"transform":{},"curve":[0.25,0,1,0]},{"duration":5,"transform":{"skX":8.98,"skY":8.98}},{"duration":5,"transform":{"skX":8.98,"skY":8.98},"curve":[0.25,0,0,1]},{"duration":3,"transform":{"skX":-13.07,"skY":-13.07}},{"duration":33,"transform":{"skX":-13.07,"skY":-13.07},"curve":[0.25,0,0.75,1]},{"duration":0,"transform":{}}],"name":"bone4"},{"frame":[{"duration":10,"transform":{},"tweenEasing":0},{"duration":5,"transform":{},"curve":[0.25,0,0.75,1]},{"duration":5,"transform":{"y":9.09,"x":3.1},"curve":[0.25,0,0,1]},{"duration":3,"transform":{"skX":-13.97,"skY":-13.97},"tweenEasing":0},{"duration":33,"transform":{"skX":-13.97,"skY":-13.97},"curve":[0.25,0,0.75,1]},{"duration":0,"transform":{}}],"name":"bone5"},{"frame":[{"duration":15,"transform":{},"tweenEasing":0},{"duration":5,"transform":{},"curve":[0.25,0,0,1]},{"duration":3,"transform":{"y":-12.06,"skX":38.92,"skY":38.92,"x":-4.61}},{"duration":33,"transform":{"y":-12.06,"skX":38.92,"skY":38.92,"x":-4.61},"curve":[0.25,0,0.75,1]},{"duration":0,"transform":{}}],"name":"bone6"},{"frame":[{"duration":10,"transform":{},"curve":[0.25,0,1,0]},{"duration":5,"transform":{"skX":29.61,"skY":29.61},"curve":[0.25,0,0.75,1]},{"duration":5,"transform":{"skX":20.33,"skY":20.33},"curve":[0.25,0,0,1]},{"duration":3,"transform":{"skX":-25.31,"skY":-25.31}},{"duration":33,"transform":{"skX":-25.31,"skY":-25.31},"curve":[0.25,0,0.75,1]},{"duration":0,"transform":{}}],"name":"bone7"},{"frame":[{"duration":10,"transform":{},"curve":[0.25,0,1,0]},{"duration":5,"transform":{"y":33.4,"skX":9.35,"skY":9.35,"x":24.93}},{"duration":5,"transform":{"y":33.4,"skX":9.35,"skY":9.35,"x":24.93},"curve":[0.25,0,0,1]},{"duration":3,"transform":{"y":4.32,"skX":105.45,"skY":105.45,"x":11.62}},{"duration":19,"transform":{"y":4.32,"skX":105.45,"skY":105.45,"x":11.62},"curve":[0.25,0,0.75,1]},{"duration":14,"transform":{"y":4.32,"skX":84.48,"skY":84.48,"x":11.62},"curve":[0.25,0,0.75,1]},{"duration":0,"transform":{}}],"name":"bone10"},{"frame":[{"duration":10,"transform":{},"curve":[0.25,0,1,0]},{"duration":5,"transform":{"skX":40.41,"skY":40.41},"curve":[0.25,0,0.75,1]},{"duration":5,"transform":{"y":-9.92,"skX":40.41,"skY":40.41,"x":-7.18},"curve":[0.25,0,0,1]},{"duration":3,"transform":{"skX":11.21,"skY":11.21},"tweenEasing":0},{"duration":19,"transform":{"skX":11.21,"skY":11.21},"curve":[0.25,0,0.75,1]},{"duration":14,"transform":{"skX":-0.39,"skY":-0.39},"curve":[0.25,0,0.75,1]},{"duration":0,"transform":{}}],"name":"bone11"},{"frame":[{"duration":15,"transform":{},"tweenEasing":0},{"duration":5,"transform":{},"curve":[0.25,0,0,1]},{"duration":22,"transform":{"skX":-9.67,"skY":-9.67}},{"duration":14,"transform":{"skX":-9.67,"skY":-9.67},"curve":[0.25,0,0.75,1]},{"duration":0,"transform":{}}],"name":"bone12"},{"frame":[{"duration":10,"transform":{},"curve":[0.25,0,1,0]},{"duration":5,"transform":{"skX":9.52,"skY":9.52}},{"duration":5,"transform":{"skX":9.52,"skY":9.52},"curve":[0.25,0,0,1]},{"duration":3,"transform":{"y":-8.02,"skX":38.36,"skY":38.36,"x":-18.94}},{"duration":33,"transform":{"y":-8.02,"skX":38.36,"skY":38.36,"x":-18.94},"curve":[0.25,0,0.75,1]},{"duration":0,"transform":{}}],"name":"bone13"},{"frame":[{"duration":10,"transform":{},"curve":[0.25,0,1,0]},{"duration":5,"transform":{"skX":-15.36,"skY":-15.36}},{"duration":5,"transform":{"skX":-15.36,"skY":-15.36},"curve":[0.25,0,0,1]},{"duration":3,"transform":{"skX":-24.76,"skY":-24.76}},{"duration":33,"transform":{"skX":-24.76,"skY":-24.76},"curve":[0.25,0,0.75,1]},{"duration":0,"transform":{}}],"name":"bone14"},{"frame":[{"duration":10,"transform":{},"curve":[0.25,0,1,0]},{"duration":5,"transform":{"skX":15.69,"skY":15.69}},{"duration":5,"transform":{"skX":15.69,"skY":15.69},"curve":[0.25,0,0,1]},{"duration":3,"transform":{"y":-5.41,"skX":3.21,"skY":3.21,"x":-4.39}},{"duration":33,"transform":{"y":-5.41,"skX":3.21,"skY":3.21,"x":-4.39},"curve":[0.25,0,0.75,1]},{"duration":0,"transform":{}}],"name":"bone16"},{"frame":[{"duration":15,"transform":{},"tweenEasing":0},{"duration":10,"transform":{},"curve":[0.25,0,0,1]},{"duration":31,"transform":{"skX":-69.65,"skY":-69.65},"curve":[0.25,0,0.75,1]},{"duration":0,"transform":{}}],"name":"bone19"},{"frame":[{"duration":15,"transform":{},"tweenEasing":0},{"duration":5,"transform":{},"curve":[0.25,0,0,1]},{"duration":3,"transform":{"skX":13.39,"skY":13.39}},{"duration":33,"transform":{"skX":13.39,"skY":13.39},"curve":[0.25,0,0.75,1]},{"duration":0,"transform":{}}],"name":"bone20"},{"frame":[{"duration":15,"transform":{},"tweenEasing":0},{"duration":5,"transform":{},"curve":[0.25,0,0,1]},{"duration":3,"transform":{"skX":-17.11,"skY":-17.11}},{"duration":33,"transform":{"skX":-17.11,"skY":-17.11},"curve":[0.25,0,0.75,1]},{"duration":0,"transform":{}}],"name":"bone21"},{"frame":[{"duration":15,"transform":{},"tweenEasing":0},{"duration":5,"transform":{},"curve":[0.25,0,0,1]},{"duration":3,"transform":{"skX":-19.78,"skY":-19.78}},{"duration":33,"transform":{"skX":-19.78,"skY":-19.78},"curve":[0.25,0,0.75,1]},{"duration":0,"transform":{}}],"name":"bone22"},{"frame":[{"duration":15,"transform":{},"tweenEasing":0},{"duration":5,"transform":{},"curve":[0.25,0,0,1]},{"duration":3,"transform":{"skX":-19,"skY":-19}},{"duration":33,"transform":{"skX":-19,"skY":-19},"curve":[0.25,0,0.75,1]},{"duration":0,"transform":{}}],"name":"bone23"},{"frame":[{"duration":15,"transform":{},"tweenEasing":0},{"duration":5,"transform":{},"curve":[0.25,0,0,1]},{"duration":3,"transform":{"y":-14.37,"skX":7.98,"skY":7.98,"x":-10.03}},{"duration":33,"transform":{"y":-14.37,"skX":7.98,"skY":7.98,"x":-10.03},"curve":[0.25,0,0.75,1]},{"duration":0,"transform":{}}],"name":"bone24"},{"frame":[{"duration":10,"transform":{},"curve":[0.25,0,1,0]},{"duration":5,"transform":{"y":7.59,"skX":25.92,"skY":25.92,"x":8.08},"curve":[0.25,0,0.75,1]},{"duration":5,"transform":{"y":7.59,"skX":14.25,"skY":14.25,"x":8.08},"curve":[0.25,0,0,1]},{"duration":3,"transform":{"skX":-30.01,"skY":-30.01},"tweenEasing":0},{"duration":33,"transform":{"skX":-30.01,"skY":-30.01},"curve":[0.25,0,0.75,1]},{"duration":0,"transform":{}}],"name":"bone25"},{"frame":[{"duration":15,"transform":{},"tweenEasing":0},{"duration":5,"transform":{},"curve":[0.25,0,0,1]},{"duration":3,"transform":{"y":5.91,"skX":-4.78,"skY":-4.78,"x":12.92}},{"duration":33,"transform":{"y":5.91,"skX":-4.78,"skY":-4.78,"x":12.92},"curve":[0.25,0,0.75,1]},{"duration":0,"transform":{}}],"name":"bone26"},{"frame":[{"duration":56,"transform":{}}],"name":"root"},{"frame":[{"duration":56,"transform":{}}],"name":"bone17"},{"frame":[{"duration":56,"transform":{}}],"name":"bone18"},{"frame":[{"duration":56,"transform":{}}],"name":"bone15"},{"frame":[{"duration":56,"transform":{}}],"name":"bone8"},{"frame":[{"duration":56,"transform":{}}],"name":"bone9"}],"slot":[{"frame":[{"tweenEasing":null,"duration":56,"displayIndex":-1}],"name":"Arm Left"},{"frame":[{"tweenEasing":null,"duration":56}],"name":"Arm LeftOver"}],"ffd":[],"ik":[],"name":"Attack D"},{"duration":60,"frame":[],"bone":[{"frame":[{"duration":10,"transform":{},"curve":[0.25,0,1,0]},{"duration":5,"transform":{"scX":0.92}},{"duration":9,"transform":{"scX":0.92},"curve":[0.25,0,0,1]},{"duration":3,"transform":{"scX":0.74,"x":-37.83}},{"duration":18,"transform":{"scX":0.74,"x":-37.83},"curve":[0.25,0,0.75,1]},{"duration":15,"transform":{"scX":1.01,"x":-37.83},"curve":[0.25,0,0.75,1]},{"duration":0,"transform":{}}],"name":"bone"},{"frame":[{"duration":10,"transform":{},"curve":[0.125,0,1,0.5]},{"duration":5,"transform":{"y":7.21,"x":39.83},"curve":[0.25,0,0.75,1]},{"duration":9,"transform":{"y":7.21,"x":60.29},"curve":[0.25,0,0,1]},{"duration":3,"transform":{"y":11.1,"skX":13.2,"skY":13.2,"x":48.08}},{"duration":20,"transform":{"y":11.1,"skX":13.2,"skY":13.2,"x":48.08},"curve":[0.25,0,0.75,1]},{"duration":13,"transform":{"y":16.29,"x":-13.07},"curve":[0.125,0,0.875,1]},{"duration":0,"transform":{}}],"name":"bone2"},{"frame":[{"duration":10,"transform":{},"tweenEasing":0},{"duration":5,"transform":{},"curve":[0.25,0,0.75,1]},{"duration":9,"transform":{"skX":-27.02,"skY":-27.02,"x":6.05},"curve":[0.25,0,0,1]},{"duration":3,"transform":{"skX":-8.95,"skY":-8.95},"tweenEasing":0},{"duration":20,"transform":{"skX":-8.95,"skY":-8.95},"curve":[0.25,0,0.75,1]},{"duration":13,"transform":{"skX":2.63,"skY":2.63},"curve":[0.25,0,0.75,1]},{"duration":0,"transform":{}}],"name":"bone3"},{"frame":[{"duration":10,"transform":{},"curve":[0.25,0,1,0]},{"duration":5,"transform":{"skX":8.98,"skY":8.98},"curve":[0.25,0,0.75,1]},{"duration":9,"transform":{"skX":-7.7,"skY":-7.7},"curve":[0.25,0,0,1]},{"duration":3,"transform":{"skX":0.58,"skY":0.58}},{"duration":20,"transform":{"skX":0.58,"skY":0.58},"curve":[0.25,0,0.75,1]},{"duration":13,"transform":{}}],"name":"bone4"},{"frame":[{"duration":10,"transform":{},"tweenEasing":0},{"duration":5,"transform":{},"curve":[0.25,0,0.75,1]},{"duration":9,"transform":{"y":4.9,"x":1.67},"curve":[0.25,0,0,1]},{"duration":3,"transform":{"skX":-4.18,"skY":-4.18},"tweenEasing":0},{"duration":20,"transform":{"skX":-4.18,"skY":-4.18},"curve":[0.25,0,0.75,1]},{"duration":13,"transform":{}}],"name":"bone5"},{"frame":[{"duration":10,"transform":{},"tweenEasing":0},{"duration":5,"transform":{},"curve":[0.25,0,0.75,1]},{"duration":9,"transform":{"skX":25.97,"skY":25.97},"curve":[0.25,0,0,1]},{"duration":3,"transform":{"y":-2.55,"skX":10.12,"skY":10.12,"x":-0.65}},{"duration":20,"transform":{"y":-2.55,"skX":10.12,"skY":10.12,"x":-0.65},"curve":[0.25,0,0.75,1]},{"duration":13,"transform":{}}],"name":"bone6"},{"frame":[{"duration":10,"transform":{},"curve":[0.25,0,1,0]},{"duration":5,"transform":{"y":-5.34,"skX":3.14,"skY":3.14,"x":4.08},"curve":[0.25,0,0.75,1]},{"duration":9,"transform":{"y":-11.12,"skX":96.46,"skY":96.46,"x":-5.73},"curve":[0.25,0,0,1]},{"duration":3,"transform":{"skX":-72.39,"skY":-72.39},"tweenEasing":0},{"duration":20,"transform":{"skX":-72.39,"skY":-72.39},"curve":[0.25,0,0.75,1]},{"duration":13,"transform":{"skX":-59.62,"skY":-59.62},"curve":[0.25,0,0.75,1]},{"duration":0,"transform":{}}],"name":"bone7"},{"frame":[{"duration":15,"transform":{},"tweenEasing":0},{"duration":9,"transform":{},"curve":[0.25,0,0,1]},{"duration":3,"transform":{"skX":-7.7,"skY":-7.7}},{"duration":20,"transform":{"skX":-7.7,"skY":-7.7},"curve":[0.25,0,0.75,1]},{"duration":13,"transform":{"skX":5.07,"skY":5.07},"curve":[0.25,0,0.75,1]},{"duration":0,"transform":{}}],"name":"bone8"},{"frame":[{"duration":15,"transform":{},"tweenEasing":0},{"duration":5,"transform":{},"curve":[0.25,0,0,1]},{"duration":2,"transform":{"skX":26.09,"skY":26.09},"curve":[0.25,0,0.75,1]},{"duration":25,"transform":{"skX":-17.32,"skY":-17.32},"curve":[0.25,0,0.75,1]},{"duration":13,"transform":{}}],"name":"bone9"},{"frame":[{"duration":10,"transform":{},"curve":[0.25,0,1,0]},{"duration":5,"transform":{"y":3.88,"skX":-32.32,"skY":-32.32,"x":4.61},"curve":[0.25,0,0.75,1]},{"duration":9,"transform":{"y":6.14,"skX":32.36,"skY":32.36,"x":-0.94},"curve":[0.25,0,0,1]},{"duration":3,"transform":{"y":4.32,"skX":-28.93,"skY":-28.93,"x":11.62}},{"duration":20,"transform":{"y":4.32,"skX":-28.93,"skY":-28.93,"x":11.62},"curve":[0.25,0,0.75,1]},{"duration":13,"transform":{"skX":-3.51,"skY":-3.51},"curve":[0.125,0,0.875,1]},{"duration":0,"transform":{}}],"name":"bone10"},{"frame":[{"duration":10,"transform":{},"curve":[0.25,0,1,0]},{"duration":5,"transform":{"skX":40.41,"skY":40.41},"curve":[0.25,0,0.75,1]},{"duration":9,"transform":{"y":-9.92,"skX":-7.14,"skY":-7.14,"x":-7.18},"curve":[0.25,0,0,1]},{"duration":3,"transform":{"skX":11.21,"skY":11.21},"tweenEasing":0},{"duration":20,"transform":{"skX":11.21,"skY":11.21},"curve":[0.25,0,0.75,1]},{"duration":13,"transform":{"skX":-0.39,"skY":-0.39},"curve":[0.25,0,0.75,1]},{"duration":0,"transform":{}}],"name":"bone11"},{"frame":[{"duration":15,"transform":{},"tweenEasing":0},{"duration":9,"transform":{},"curve":[0.25,0,0,1]},{"duration":23,"transform":{"skX":-9.67,"skY":-9.67}},{"duration":13,"transform":{"skX":-9.67,"skY":-9.67},"curve":[0.25,0,0.75,1]},{"duration":0,"transform":{}}],"name":"bone12"},{"frame":[{"duration":10,"transform":{},"curve":[0.25,0,1,0]},{"duration":5,"transform":{"skX":9.52,"skY":9.52}},{"duration":9,"transform":{"skX":9.52,"skY":9.52},"curve":[0.25,0,0,1]},{"duration":3,"transform":{"y":-7.96,"skX":14.35,"skY":14.35,"x":-7.04}},{"duration":20,"transform":{"y":-7.96,"skX":14.35,"skY":14.35,"x":-7.04},"curve":[0.25,0,0.75,1]},{"duration":13,"transform":{"skX":1.65,"skY":1.65},"curve":[0.125,0,0.875,1]},{"duration":0,"transform":{}}],"name":"bone13"},{"frame":[{"duration":10,"transform":{},"curve":[0.25,0,1,0]},{"duration":5,"transform":{"skX":-15.36,"skY":-15.36}},{"duration":9,"transform":{"skX":-15.36,"skY":-15.36},"curve":[0.25,0,0,1]},{"duration":3,"transform":{"skX":-24.76,"skY":-24.76}},{"duration":20,"transform":{"skX":-24.76,"skY":-24.76},"curve":[0.25,0,0.75,1]},{"duration":13,"transform":{"skX":-7.75,"skY":-7.75},"curve":[0.25,0,0.75,1]},{"duration":0,"transform":{}}],"name":"bone14"},{"frame":[{"duration":10,"transform":{},"curve":[0.25,0,1,0]},{"duration":5,"transform":{"skX":15.69,"skY":15.69}},{"duration":9,"transform":{"skX":15.69,"skY":15.69},"curve":[0.25,0,0,1]},{"duration":3,"transform":{"y":-5.41,"skX":3.21,"skY":3.21,"x":-4.39}},{"duration":20,"transform":{"y":-5.41,"skX":3.21,"skY":3.21,"x":-4.39},"curve":[0.25,0,0.75,1]},{"duration":13,"transform":{"skX":13.37,"skY":13.37},"curve":[0.125,0,0.875,1]},{"duration":0,"transform":{}}],"name":"bone16"},{"frame":[{"duration":15,"transform":{},"tweenEasing":0},{"duration":9,"transform":{},"curve":[0.25,0,0,1]},{"duration":3,"transform":{"skX":-56.58,"skY":-56.58}},{"duration":20,"transform":{"skX":-56.58,"skY":-56.58},"curve":[0.25,0,0.75,1]},{"duration":13,"transform":{}}],"name":"bone19"},{"frame":[{"duration":10,"transform":{},"curve":[0.25,0,1,0]},{"duration":5,"transform":{"skX":20.16,"skY":20.16},"curve":[0.25,0,0.75,1]},{"duration":9,"transform":{"skX":26.4,"skY":26.4},"curve":[0.663,0.15,0.463,1]},{"duration":3,"transform":{"skX":13.39,"skY":13.39}},{"duration":20,"transform":{"skX":13.39,"skY":13.39},"curve":[0.25,0,0.75,1]},{"duration":13,"transform":{"skX":6.57,"skY":6.57},"curve":[0.25,0,0.75,1]},{"duration":0,"transform":{}}],"name":"bone20"},{"frame":[{"duration":10,"transform":{},"curve":[0.25,0,1,0]},{"duration":5,"transform":{"skX":13.88,"skY":13.88},"curve":[0.25,0,0.75,1]},{"duration":1,"transform":{"skX":11.63,"skY":11.63},"curve":[0.413,0,0.735,0.36]},{"duration":8,"transform":{"skX":24.88,"skY":24.88},"curve":[0.153,0.18,0.047,1]},{"duration":3,"transform":{"skX":-17.11,"skY":-17.11}},{"duration":20,"transform":{"skX":-17.11,"skY":-17.11},"curve":[0.25,0,0.75,1]},{"duration":13,"transform":{"skX":-1.06,"skY":-1.06},"curve":[0.25,0,0.75,1]},{"duration":0,"transform":{}}],"name":"bone21"},{"frame":[{"duration":10,"transform":{},"tweenEasing":0},{"duration":8,"transform":{},"curve":[0.25,0,0.75,1]},{"duration":5,"transform":{"skX":7.96,"skY":7.96},"curve":[0.25,0,0.431,0.85]},{"duration":37,"transform":{"skX":-36.57,"skY":-36.57},"curve":[0.25,0,0.75,1]},{"duration":0,"transform":{}}],"name":"bone22"},{"frame":[{"duration":10,"transform":{},"tweenEasing":0},{"duration":5,"transform":{},"curve":[0.25,0,0.75,1]},{"duration":9,"transform":{"skX":26.01,"skY":26.01},"curve":[0.25,0,0,1]},{"duration":3,"transform":{"skX":-19,"skY":-19}},{"duration":20,"transform":{"skX":-19,"skY":-19},"curve":[0.25,0,0.75,1]},{"duration":13,"transform":{"skX":-21.44,"skY":-21.44},"curve":[0.25,0,0.75,1]},{"duration":0,"transform":{}}],"name":"bone23"},{"frame":[{"duration":10,"transform":{},"curve":[0.25,0,1,0]},{"duration":5,"transform":{"skX":8.26,"skY":8.26},"curve":[0.25,0,0.75,1]},{"duration":9,"transform":{},"curve":[0.25,0,0,1]},{"duration":3,"transform":{"y":-14.37,"skX":11.41,"skY":11.41,"x":-10.03}},{"duration":20,"transform":{"y":-14.37,"skX":11.41,"skY":11.41,"x":-10.03},"curve":[0.25,0,0.75,1]},{"duration":13,"transform":{"skX":3.81,"skY":3.81},"curve":[0.125,0,0.875,1]},{"duration":0,"transform":{}}],"name":"bone24"},{"frame":[{"duration":10,"transform":{},"curve":[0.25,0,1,0]},{"duration":5,"transform":{"y":5.55,"skX":16.09,"skY":16.09,"x":8},"curve":[0.25,0,0.75,1]},{"duration":8,"transform":{"y":7.59,"skX":47.35,"skY":47.35,"x":8.08},"curve":[0.213,0.06,0.175,0.98]},{"duration":11,"transform":{"skX":-72.86,"skY":-72.86},"curve":[0.429,0.07,0.875,1]},{"duration":10,"transform":{"skX":-49.75,"skY":-49.75},"curve":[0.363,0.44,0.755,1]},{"duration":16,"transform":{"skX":-35.64,"skY":-35.64},"curve":[0.258,0,0.619,0.45]},{"duration":0,"transform":{}}],"name":"bone25"},{"frame":[{"duration":10,"transform":{},"tweenEasing":0},{"duration":5,"transform":{},"curve":[0.25,0,0.75,1]},{"duration":5,"transform":{"skX":9.95,"skY":9.95},"curve":[0.25,0,0,1]},{"duration":7,"transform":{"y":5.91,"skX":0.77,"skY":0.77,"x":12.92},"curve":[0.25,0,0.75,1]},{"duration":20,"transform":{"y":5.91,"skX":-15.64,"skY":-15.64,"x":12.92},"curve":[0.25,0,0.75,1]},{"duration":13,"transform":{"skX":0.94,"skY":0.94},"curve":[0.125,0,0.875,1]},{"duration":0,"transform":{}}],"name":"bone26"},{"frame":[{"duration":60,"transform":{}}],"name":"root"},{"frame":[{"duration":60,"transform":{}}],"name":"bone17"},{"frame":[{"duration":60,"transform":{}}],"name":"bone18"},{"frame":[{"duration":60,"transform":{}}],"name":"bone15"}],"slot":[],"ffd":[],"ik":[],"name":"Attack E"},{"duration":56,"frame":[],"bone":[{"frame":[{"duration":10,"transform":{},"curve":[0.25,0,1,0]},{"duration":5,"transform":{"scX":0.92}},{"duration":5,"transform":{"scX":0.92},"curve":[0.25,0,0,1]},{"duration":3,"transform":{"scX":0.74,"x":-37.83}},{"duration":18,"transform":{"scX":0.74,"x":-37.83},"curve":[0.25,0,0.75,1]},{"duration":15,"transform":{"scX":1.01,"x":-37.83},"curve":[0.25,0,0.75,1]},{"duration":0,"transform":{}}],"name":"bone"},{"frame":[{"duration":10,"transform":{},"curve":[0.125,0,1,0.5]},{"duration":5,"transform":{"y":7.21,"x":39.83},"curve":[0.25,0,0.75,1]},{"duration":5,"transform":{"y":7.21,"x":60.29},"curve":[0.25,0,0,1]},{"duration":3,"transform":{"y":11.1,"skX":-8.4,"skY":-8.4,"x":-73.55}},{"duration":18,"transform":{"y":11.1,"skX":-8.4,"skY":-8.4,"x":-73.55},"curve":[0.25,0,0.75,1]},{"duration":15,"transform":{"y":16.29,"x":-13.07},"curve":[0.125,0,0.875,1]},{"duration":0,"transform":{}}],"name":"bone2"},{"frame":[{"duration":10,"transform":{},"tweenEasing":0},{"duration":5,"transform":{},"curve":[0.25,0,0.75,1]},{"duration":5,"transform":{"x":6.05},"curve":[0.25,0,0,1]},{"duration":3,"transform":{"skX":21.63,"skY":21.63},"tweenEasing":0},{"duration":18,"transform":{"skX":21.63,"skY":21.63},"curve":[0.25,0,0.75,1]},{"duration":15,"transform":{"skX":2.63,"skY":2.63},"curve":[0.25,0,0.75,1]},{"duration":0,"transform":{}}],"name":"bone3"},{"frame":[{"duration":10,"transform":{},"curve":[0.25,0,1,0]},{"duration":5,"transform":{"skX":8.98,"skY":8.98}},{"duration":5,"transform":{"skX":8.98,"skY":8.98},"curve":[0.25,0,0,1]},{"duration":3,"transform":{"skX":11.08,"skY":11.08}},{"duration":18,"transform":{"skX":11.08,"skY":11.08},"curve":[0.25,0,0.75,1]},{"duration":15,"transform":{}}],"name":"bone4"},{"frame":[{"duration":10,"transform":{},"tweenEasing":0},{"duration":5,"transform":{},"curve":[0.25,0,0.75,1]},{"duration":5,"transform":{"y":9.09,"x":3.1},"curve":[0.25,0,0,1]},{"duration":3,"transform":{"skX":-21.18,"skY":-21.18},"tweenEasing":0},{"duration":18,"transform":{"skX":-21.18,"skY":-21.18},"curve":[0.25,0,0.75,1]},{"duration":15,"transform":{}}],"name":"bone5"},{"frame":[{"duration":15,"transform":{},"tweenEasing":0},{"duration":5,"transform":{},"curve":[0.25,0,0,1]},{"duration":3,"transform":{"y":-6.93,"skX":38.92,"skY":38.92,"x":-3.71}},{"duration":18,"transform":{"y":-6.93,"skX":38.92,"skY":38.92,"x":-3.71},"curve":[0.25,0,0.75,1]},{"duration":15,"transform":{}}],"name":"bone6"},{"frame":[{"duration":10,"transform":{},"curve":[0.25,0,1,0]},{"duration":5,"transform":{"skX":29.61,"skY":29.61},"curve":[0.25,0,0.75,1]},{"duration":5,"transform":{"skX":20.33,"skY":20.33},"curve":[0.25,0,0,1]},{"duration":3,"transform":{"skX":-41.64,"skY":-41.64}},{"duration":18,"transform":{"skX":-41.64,"skY":-41.64},"curve":[0.25,0,0.75,1]},{"duration":15,"transform":{}}],"name":"bone7"},{"frame":[{"duration":20,"transform":{},"tweenEasing":0},{"duration":10,"transform":{},"curve":[0.25,0,0.75,1]},{"duration":11,"transform":{"skX":-32.88,"skY":-32.88},"curve":[0.25,0,0.75,1]},{"duration":15,"transform":{}}],"name":"bone9"},{"frame":[{"duration":10,"transform":{},"curve":[0.25,0,1,0]},{"duration":5,"transform":{"y":33.4,"skX":9.35,"skY":9.35,"x":24.93},"curve":[0.243,0,0.68,0.71]},{"duration":5,"transform":{"y":33.4,"scY":-0.95,"skX":-10.54,"skY":-10.54,"x":24.93},"curve":[0.34375,0.465,0.5369999999999999,1]},{"duration":3,"transform":{"y":1.78,"scY":-1.322,"skX":105.45,"skY":105.45,"x":14.76}},{"duration":18,"transform":{"y":1.78,"scY":-1.322,"skX":105.45,"skY":105.45,"x":14.76},"curve":[0.25,0,0.75,1]},{"duration":12,"transform":{"y":3.24,"scY":-1.322,"skX":105.45,"skY":105.45,"x":5.95},"curve":[0.243,0,0.68,0.71]},{"duration":1,"transform":{"y":3.54,"scY":-1.322,"skX":10.1,"skY":10.1,"x":0.51}},{"duration":2,"transform":{"y":3.56,"skX":3.04,"skY":3.04,"x":0.1},"curve":[0.183,0.315,0.8514999999999999,1]},{"duration":0,"transform":{"y":3.58,"skX":-4.17,"skY":-4.17,"x":-0.31}}],"name":"bone10"},{"frame":[{"duration":10,"transform":{},"curve":[0.25,0,1,0]},{"duration":5,"transform":{"skX":40.41,"skY":40.41},"curve":[0.25,0,0.75,1]},{"duration":5,"transform":{"y":-9.92,"skX":9.75,"skY":9.75,"x":-7.18},"curve":[0.25,0,0,1]},{"duration":3,"transform":{"skX":-36.36,"skY":-36.36},"tweenEasing":0},{"duration":18,"transform":{"skX":-36.36,"skY":-36.36},"curve":[0.25,0,0.75,1]},{"duration":15,"transform":{"skX":-0.39,"skY":-0.39},"curve":[0.25,0,0.75,1]},{"duration":0,"transform":{}}],"name":"bone11"},{"frame":[{"duration":15,"transform":{},"tweenEasing":0},{"duration":5,"transform":{},"curve":[0.25,0,0,1]},{"duration":21,"transform":{"skX":-9.67,"skY":-9.67}},{"duration":15,"transform":{"skX":-9.67,"skY":-9.67},"curve":[0.25,0,0.75,1]},{"duration":0,"transform":{}}],"name":"bone12"},{"frame":[{"duration":10,"transform":{},"curve":[0.25,0,1,0]},{"duration":5,"transform":{"skX":9.52,"skY":9.52}},{"duration":5,"transform":{"skX":9.52,"skY":9.52},"curve":[0.25,0,0,1]},{"duration":3,"transform":{"y":-7.96,"skX":14.35,"skY":14.35,"x":-7.04}},{"duration":18,"transform":{"y":-7.96,"skX":14.35,"skY":14.35,"x":-7.04},"curve":[0.25,0,0.75,1]},{"duration":15,"transform":{"skX":1.65,"skY":1.65},"curve":[0.125,0,0.875,1]},{"duration":0,"transform":{}}],"name":"bone13"},{"frame":[{"duration":10,"transform":{},"curve":[0.25,0,1,0]},{"duration":5,"transform":{"skX":-15.36,"skY":-15.36}},{"duration":5,"transform":{"skX":-15.36,"skY":-15.36},"curve":[0.25,0,0,1]},{"duration":3,"transform":{"skX":-24.76,"skY":-24.76}},{"duration":18,"transform":{"skX":-24.76,"skY":-24.76},"curve":[0.25,0,0.75,1]},{"duration":15,"transform":{"skX":-7.75,"skY":-7.75},"curve":[0.25,0,0.75,1]},{"duration":0,"transform":{}}],"name":"bone14"},{"frame":[{"duration":10,"transform":{},"curve":[0.25,0,1,0]},{"duration":5,"transform":{"skX":15.69,"skY":15.69}},{"duration":5,"transform":{"skX":15.69,"skY":15.69},"curve":[0.25,0,0,1]},{"duration":3,"transform":{"y":-5.41,"skX":3.21,"skY":3.21,"x":-4.39}},{"duration":18,"transform":{"y":-5.41,"skX":3.21,"skY":3.21,"x":-4.39},"curve":[0.25,0,0.75,1]},{"duration":15,"transform":{"skX":13.37,"skY":13.37},"curve":[0.125,0,0.875,1]},{"duration":0,"transform":{}}],"name":"bone16"},{"frame":[{"duration":15,"transform":{},"tweenEasing":0},{"duration":5,"transform":{},"curve":[0.25,0,0,1]},{"duration":3,"transform":{"skX":-31,"skY":-31}},{"duration":18,"transform":{"skX":-31,"skY":-31},"curve":[0.25,0,0.75,1]},{"duration":15,"transform":{}}],"name":"bone19"},{"frame":[{"duration":15,"transform":{},"tweenEasing":0},{"duration":5,"transform":{},"curve":[0.25,0,0,1]},{"duration":3,"transform":{"skX":-12.86,"skY":-12.86}},{"duration":18,"transform":{"skX":-12.86,"skY":-12.86},"curve":[0.25,0,0.75,1]},{"duration":15,"transform":{"skX":6.57,"skY":6.57},"curve":[0.25,0,0.75,1]},{"duration":0,"transform":{}}],"name":"bone20"},{"frame":[{"duration":15,"transform":{},"tweenEasing":0},{"duration":5,"transform":{},"curve":[0.25,0,0,1]},{"duration":3,"transform":{"skX":22.14,"skY":22.14}},{"duration":18,"transform":{"skX":22.14,"skY":22.14},"curve":[0.25,0,0.75,1]},{"duration":15,"transform":{"skX":-1.06,"skY":-1.06},"curve":[0.25,0,0.75,1]},{"duration":0,"transform":{}}],"name":"bone21"},{"frame":[{"duration":15,"transform":{},"curve":[0.25,0,1,0]},{"duration":4,"transform":{"skX":-8.31,"skY":-8.31},"curve":[0.25,0,0.75,1]},{"duration":6,"transform":{},"curve":[0.25,0,0,1]},{"duration":16,"transform":{"skX":9.47,"skY":9.47},"curve":[0.25,0,0.75,1]},{"duration":15,"transform":{}}],"name":"bone22"},{"frame":[{"duration":15,"transform":{},"tweenEasing":0},{"duration":5,"transform":{},"curve":[0.25,0,0,1]},{"duration":3,"transform":{"skX":-14.21,"skY":-14.21}},{"duration":18,"transform":{"skX":-14.21,"skY":-14.21},"curve":[0.25,0,0.75,1]},{"duration":15,"transform":{"skX":-21.44,"skY":-21.44},"curve":[0.25,0,0.75,1]},{"duration":0,"transform":{}}],"name":"bone23"},{"frame":[{"duration":10,"transform":{},"curve":[0.231,0,0.883,0]},{"duration":2,"transform":{"skX":23.11,"skY":23.11},"curve":[0.649,0.3,1,0.63]},{"duration":4,"transform":{"skX":32.83,"skY":32.83},"curve":[0.25,0,0.75,1]},{"duration":4,"transform":{"skX":13.25,"skY":13.25},"curve":[0.25,0,0.385,0.9]},{"duration":26,"transform":{"y":-14.37,"skX":42.87,"skY":42.87,"x":-10.03},"curve":[0.25,0,0.54,0.92]},{"duration":10,"transform":{"skX":-6.65,"skY":-6.65},"curve":[0.125,0,0.875,1]},{"duration":0,"transform":{}}],"name":"bone24"},{"frame":[{"duration":10,"transform":{},"curve":[0.25,0,1,0]},{"duration":5,"transform":{"y":7.59,"skX":25.92,"skY":25.92,"x":8.08},"curve":[0.25,0,0.75,1]},{"duration":5,"transform":{"y":7.59,"skX":22.98,"skY":22.98,"x":8.08},"curve":[0.25,0,0,1]},{"duration":7,"transform":{"skX":-42.06,"skY":-42.06},"curve":[0.125,0,0.875,1]},{"duration":14,"transform":{"skX":-52.11,"skY":-52.11},"curve":[0.302,0,0.638,0.36]},{"duration":15,"transform":{"skX":-8.45,"skY":-8.45},"curve":[0.25,0,0.75,1]},{"duration":0,"transform":{}}],"name":"bone25"},{"frame":[{"duration":10,"transform":{},"curve":[0.231,0,0.883,0]},{"duration":2,"transform":{"skX":19.91,"skY":19.91},"curve":[0.649,0.3,1,0.63]},{"duration":4,"transform":{"skX":26.32,"skY":26.32},"curve":[0.25,0,0.75,1]},{"duration":4,"transform":{},"curve":[0.25,0,0.385,0.9]},{"duration":26,"transform":{"y":5.91,"skX":38.63,"skY":38.63,"x":12.92},"curve":[0.25,0,0.54,0.92]},{"duration":10,"transform":{"skX":-9.52,"skY":-9.52},"curve":[0.125,0,0.875,1]},{"duration":0,"transform":{}}],"name":"bone26"},{"frame":[{"duration":56,"transform":{}}],"name":"root"},{"frame":[{"duration":56,"transform":{}}],"name":"bone17"},{"frame":[{"duration":56,"transform":{}}],"name":"bone18"},{"frame":[{"duration":56,"transform":{}}],"name":"bone15"},{"frame":[{"duration":56,"transform":{}}],"name":"bone8"}],"slot":[{"frame":[{"tweenEasing":0,"duration":15},{"tweenEasing":0,"duration":39,"displayIndex":-1},{"tweenEasing":null,"duration":2}],"name":"Arm Left"},{"frame":[{"tweenEasing":0,"duration":15,"displayIndex":-1},{"tweenEasing":0,"duration":39},{"tweenEasing":null,"duration":2,"displayIndex":-1}],"name":"Arm LeftOver"}],"ffd":[],"ik":[],"name":"Attack F"},{"duration":30,"frame":[],"bone":[{"frame":[{"duration":10,"transform":{},"curve":[0.25,0,0,1]},{"duration":20,"transform":{"scX":1.12,"x":35.8},"curve":[0.25,0,0.75,1]},{"duration":0,"transform":{}}],"name":"bone"},{"frame":[{"duration":10,"transform":{},"curve":[0.25,0,0,1]},{"duration":20,"transform":{"y":5.6,"x":68.41},"curve":[0.25,0,0.75,1]},{"duration":0,"transform":{}}],"name":"bone2"},{"frame":[{"duration":10,"transform":{},"curve":[0.25,0,0,1]},{"duration":20,"transform":{"y":0.52,"skX":30.8,"skY":30.8,"x":-4.34},"curve":[0.25,0,0.75,1]},{"duration":0,"transform":{}}],"name":"bone7"},{"frame":[{"duration":10,"transform":{},"curve":[0.25,0,0,1]},{"duration":20,"transform":{"skX":11.5,"skY":11.5},"curve":[0.25,0,0.75,1]},{"duration":0,"transform":{}}],"name":"bone10"},{"frame":[{"duration":10,"transform":{},"curve":[0.25,0,0,1]},{"duration":20,"transform":{"skX":20.28,"skY":20.28},"curve":[0.25,0,0.75,1]},{"duration":0,"transform":{}}],"name":"bone11"},{"frame":[{"duration":10,"transform":{},"curve":[0.25,0,0,1]},{"duration":20,"transform":{"y":-1.94,"skX":17.99,"skY":17.99,"x":-10.04},"curve":[0.25,0,0.75,1]},{"duration":0,"transform":{}}],"name":"bone13"},{"frame":[{"duration":10,"transform":{},"curve":[0.25,0,0,1]},{"duration":20,"transform":{"skX":-10.51,"skY":-10.51},"curve":[0.25,0,0.75,1]},{"duration":0,"transform":{}}],"name":"bone14"},{"frame":[{"duration":10,"transform":{},"curve":[0.25,0,0,1]},{"duration":20,"transform":{"skX":24.87,"skY":24.87},"curve":[0.25,0,0.75,1]},{"duration":0,"transform":{}}],"name":"bone16"},{"frame":[{"duration":10,"transform":{},"curve":[0.25,0,0,1]},{"duration":20,"transform":{"skX":20.16,"skY":20.16},"curve":[0.25,0,0.75,1]},{"duration":0,"transform":{}}],"name":"bone20"},{"frame":[{"duration":10,"transform":{},"curve":[0.25,0,0,1]},{"duration":20,"transform":{"skX":37.25,"skY":37.25},"curve":[0.25,0,0.75,1]},{"duration":0,"transform":{}}],"name":"bone21"},{"frame":[{"duration":10,"transform":{},"curve":[0.25,0,0,1]},{"duration":20,"transform":{"skX":29.13,"skY":29.13},"curve":[0.25,0,0.75,1]},{"duration":0,"transform":{}}],"name":"bone24"},{"frame":[{"duration":10,"transform":{},"curve":[0.25,0,0,1]},{"duration":20,"transform":{"y":6.48,"skX":19.75,"skY":19.75,"x":5.38},"curve":[0.25,0,0.75,1]},{"duration":0,"transform":{}}],"name":"bone25"},{"frame":[{"duration":10,"transform":{},"curve":[0.25,0,0,1]},{"duration":20,"transform":{"skX":29.79,"skY":29.79},"curve":[0.25,0,0.75,1]},{"duration":0,"transform":{}}],"name":"bone26"},{"frame":[{"duration":30,"transform":{}}],"name":"root"},{"frame":[{"duration":30,"transform":{}}],"name":"bone3"},{"frame":[{"duration":30,"transform":{}}],"name":"bone4"},{"frame":[{"duration":30,"transform":{}}],"name":"bone17"},{"frame":[{"duration":30,"transform":{}}],"name":"bone5"},{"frame":[{"duration":30,"transform":{}}],"name":"bone18"},{"frame":[{"duration":30,"transform":{}}],"name":"bone15"},{"frame":[{"duration":30,"transform":{}}],"name":"bone6"},{"frame":[{"duration":30,"transform":{}}],"name":"bone22"},{"frame":[{"duration":30,"transform":{}}],"name":"bone8"},{"frame":[{"duration":30,"transform":{}}],"name":"bone19"},{"frame":[{"duration":30,"transform":{}}],"name":"bone23"},{"frame":[{"duration":30,"transform":{}}],"name":"bone9"},{"frame":[{"duration":30,"transform":{}}],"name":"bone12"}],"slot":[],"ffd":[],"ik":[],"name":"Damage"},{"duration":60,"frame":[],"bone":[{"frame":[{"duration":30,"transform":{},"curve":[0.276,0,0.621,0.4]},{"duration":30,"transform":{"scX":0.76},"curve":[0.314,0.27,0.657,0.64]},{"duration":0,"transform":{}}],"name":"bone"},{"frame":[{"duration":27,"transform":{},"curve":[0.25,0,0.75,1]},{"duration":33,"transform":{"y":-23.24},"curve":[0.25,0,0.75,1]},{"duration":0,"transform":{}}],"name":"bone2"},{"frame":[{"duration":19,"transform":{},"curve":[0.25,0,0.75,1]},{"duration":41,"transform":{"skX":1.64,"skY":1.64},"curve":[0.628,0.13,0.75,1]},{"duration":0,"transform":{}}],"name":"bone4"},{"frame":[{"duration":34,"transform":{},"curve":[0.25,0,0.75,1]},{"duration":26,"transform":{"skX":-10.98,"skY":-10.98},"curve":[0.25,0,0.75,1]},{"duration":0,"transform":{}}],"name":"bone7"},{"frame":[{"duration":33,"transform":{},"curve":[0.25,0,0.75,1]},{"duration":27,"transform":{"skX":4.18,"skY":4.18},"curve":[0.25,0,0.75,1]},{"duration":0,"transform":{}}],"name":"bone8"},{"frame":[{"duration":45,"transform":{},"curve":[0.242,0,0.667,0.67]},{"duration":15,"transform":{"skX":-4.78,"skY":-4.78},"curve":[0.379,0.6,0.724,1]},{"duration":0,"transform":{}}],"name":"bone9"},{"frame":[{"duration":26,"transform":{},"curve":[0.25,0,0.75,1]},{"duration":34,"transform":{"skX":-7.31,"skY":-7.31},"curve":[0.25,0,0.75,1]},{"duration":0,"transform":{}}],"name":"bone10"},{"frame":[{"duration":36,"transform":{},"curve":[0.25,0,0.75,1]},{"duration":24,"transform":{"skX":6.02,"skY":6.02},"curve":[0.25,0,0.75,1]},{"duration":0,"transform":{}}],"name":"bone11"},{"frame":[{"duration":30,"transform":{},"curve":[0.25,0,0.75,1]},{"duration":30,"transform":{"skX":7.98,"skY":7.98},"curve":[0.25,0,0.75,1]},{"duration":0,"transform":{}}],"name":"bone13"},{"frame":[{"duration":30,"transform":{},"curve":[0.25,0,0.75,1]},{"duration":30,"transform":{"skX":-15.87,"skY":-15.87},"curve":[0.25,0,0.75,1]},{"duration":0,"transform":{}}],"name":"bone14"},{"frame":[{"duration":30,"transform":{},"curve":[0.25,0,0.75,1]},{"duration":30,"transform":{"skX":9.24,"skY":9.24},"curve":[0.25,0,0.75,1]},{"duration":0,"transform":{}}],"name":"bone16"},{"frame":[{"duration":30,"transform":{},"curve":[0.25,0,0.75,1]},{"duration":30,"transform":{"skX":5.23,"skY":5.23},"curve":[0.25,0,0.75,1]},{"duration":0,"transform":{}}],"name":"bone17"},{"frame":[{"duration":33,"transform":{},"curve":[0.25,0,0.75,1]},{"duration":27,"transform":{"skX":-6.66,"skY":-6.66},"curve":[0.25,0,0.75,1]},{"duration":0,"transform":{}}],"name":"bone20"},{"frame":[{"duration":36,"transform":{},"curve":[0.25,0,0.75,1]},{"duration":24,"transform":{"skX":14.13,"skY":14.13},"curve":[0.639,0,0.75,1]},{"duration":0,"transform":{}}],"name":"bone21"},{"frame":[{"duration":24,"transform":{},"curve":[0.25,0,0.75,1]},{"duration":36,"transform":{"skX":-17.6,"skY":-17.6},"curve":[0.25,0,0.75,1]},{"duration":0,"transform":{}}],"name":"bone23"},{"frame":[{"duration":28,"transform":{},"curve":[0.25,0,0.75,1]},{"duration":32,"transform":{"skX":15.48,"skY":15.48},"curve":[0.25,0,0.75,1]},{"duration":0,"transform":{}}],"name":"bone24"},{"frame":[{"duration":35,"transform":{},"curve":[0.25,0,0.75,1]},{"duration":25,"transform":{"y":-0.63,"skX":-15.97,"skY":-15.97,"x":5.23},"curve":[0.25,0,0.75,1]},{"duration":0,"transform":{}}],"name":"bone25"},{"frame":[{"duration":34,"transform":{},"curve":[0.25,0,0.75,1]},{"duration":26,"transform":{"skX":14.3,"skY":14.3},"curve":[0.25,0,0.75,1]},{"duration":0,"transform":{}}],"name":"bone26"},{"frame":[{"duration":60,"transform":{}}],"name":"root"},{"frame":[{"duration":60,"transform":{}}],"name":"bone3"},{"frame":[{"duration":60,"transform":{}}],"name":"bone5"},{"frame":[{"duration":60,"transform":{}}],"name":"bone18"},{"frame":[{"duration":60,"transform":{}}],"name":"bone15"},{"frame":[{"duration":60,"transform":{}}],"name":"bone6"},{"frame":[{"duration":60,"transform":{}}],"name":"bone22"},{"frame":[{"duration":60,"transform":{}}],"name":"bone19"},{"frame":[{"duration":60,"transform":{}}],"name":"bone12"}],"slot":[],"ffd":[{"frame":[{"duration":30,"offset":0,"vertices":[],"tweenEasing":0},{"duration":30,"offset":31,"vertices":[-0.43,0,-0.43,0,-0.43,0,0,0,0,0,0,0,0,0,0,0,0,0,0,0,0,0,0,0,0,0,0,0,0,0,0,0,0,0,0,0,0,0,0,0,0,0,0,0,0,0,0,0,0,0,0,0,0,0,0,0,0,0,0,0,0,0,0,0,0,0,0,0,0,0,0,0,0,0,0,0,0,0,0,0,0,0,0,0,0,0,0,0,0,0,0,0,0,0,0,0,0,0,0,0,0,0,-0.43,0,-0.43,0,-0.43,0,-0.43,0,0,0,-0.43,0,-0.43,0,-0.43,0,-0.43,0,-0.43,0,-0.42,0,0,0,0,0,0,0,0,0,0,0,0,0,0,0,0,0,0,0,0,0,0,0,0,0,0,0,0,0,0,0,0,0,0,0,0,0,-0.43,0,0,0,0,0,0,0,0],"tweenEasing":0},{"duration":0,"offset":0,"vertices":[],"tweenEasing":null}],"scale":1,"slot":"Layer 37","offset":0,"name":"Layer 37","skin":""}],"ik":[],"name":"Idle"}],"defaultActions":[{"gotoAndPlay":"Attack A"}],"name":"Azrafel","frameRate":30,"skin":[{"name":"","slot":[{"display":[{"path":"Ellipse 2","type":"image","name":"Ellipse 2","transform":{"y":3.54,"x":8.1}}],"name":"Ellipse 2"},{"display":[{"slotPose":[1,0,0,1,0,0],"vertices":[39.2,-206.3,34.33,-221.47,39.14,-225.04,36.5,-228.45,36.43,-238.55,41.82,-241.26,39.65,-262.14,41.33,-273.81,33.97,-282.62,30.32,-293.28,22.59,-299.34,19.26,-313.37,22.83,-319.22,27.34,-321.62,36.76,-322.3,46.11,-320.37,49.67,-315.91,51.39,-304.43,59.38,-296.54,61.83,-287.51,66.26,-280.17,64.75,-269.61,64.37,-257.13,60.77,-239.38,64.01,-236.63,62.76,-226.65,57.15,-224.54,57.43,-216.57,55.07,-212.25,53.67,-212.02,53.2,-210.19,50.41,-209.52,48.97,-208.04,46.38,-208.17,46.14,-206.3,50.03,-224.31,50.27,-230.54,51.62,-237.03,48.68,-216.91,53.34,-257.91,53.77,-277.21,47.1,-291.06,42.26,-300.61,36.35,-312.08],"path":"Arm right","edges":[11,10,10,9,9,8,8,7,7,6,6,5,5,4,4,3,3,2,2,1,1,0,0,34,34,33,33,32,32,31,31,30,30,29,29,28,28,27,27,26,26,25,25,24,24,23,23,22,22,21,21,20,20,19,19,18,18,17,17,16,16,15,15,14,14,13,13,12,12,11],"name":"Arm right","type":"mesh","triangles":[21,39,22,39,23,22,40,21,20,19,40,20,36,26,25,40,39,21,23,37,24,37,36,24,36,25,24,39,37,23,18,41,19,41,40,19,5,37,39,40,7,39,17,41,18,7,6,39,29,28,27,38,29,27,35,38,27,35,27,26,36,35,26,42,41,17,38,31,29,41,7,40,6,5,39,31,30,29,8,7,41,38,33,31,5,36,37,16,43,17,43,42,17,5,3,36,33,32,31,36,2,35,2,38,35,15,43,16,3,2,36,4,3,5,0,33,38,1,0,38,2,1,38,42,9,41,9,8,41,14,43,15,33,0,34,43,9,42,10,9,43,11,10,43,13,43,14,13,12,43,12,11,43],"bonePose":[22,-0.08976347271150542,0.9959631112479876,-0.9959631112479876,-0.08976347271150542,55.24634386904228,-276.9733040819078,23,-0.22495105434386495,0.9743700647852354,-0.9743700647852354,-0.22495105434386495,50.9208201411918,-224.07804583998404,14,0.5138407419213795,0.8578855937371175,-0.8578855937371175,0.5138407419213795,35.879686306025484,-309.3070121098598],"uvs":[0.42432,1,0.3206,0.86924,0.42294,0.83843,0.36663,0.80904,0.36535,0.72202,0.47982,0.69858,0.4338,0.51857,0.46955,0.41802,0.31295,0.34204,0.23533,0.25018,0.07078,0.19791,0,0.07708,0.07588,0.0266,0.17188,0.00591,0.37205,0,0.5712,0.01667,0.64677,0.05515,0.68353,0.15405,0.85348,0.22208,0.90557,0.29987,1,0.36318,0.96788,0.45423,0.95971,0.56181,0.88312,0.71492,0.95208,0.73852,0.92553,0.82459,0.80604,0.8428,0.81217,0.91149,0.76184,0.94865,0.73223,0.95072,0.72201,0.96644,0.66278,0.97224,0.63214,0.98506,0.577,0.98382,0.57189,1,0.65461,0.84479,0.65972,0.791,0.68831,0.73514,0.62602,0.90851,0.72508,0.55511,0.73427,0.38875,0.59231,0.26934,0.48917,0.187,0.36355,0.0881],"width":47,"weights":[2,22,0.0039,23,0.9961,2,22,0.28742,23,0.71258,2,22,0.59494,23,0.40506,2,22,0.8702,23,0.1298,2,22,0.99975,23,0.00025,1,22,1,2,14,0.04285,22,0.95715,2,14,0.53346,22,0.46654,2,14,0.96704,22,0.03296,1,14,1,1,14,1,1,14,1,1,14,1,1,14,1,1,14,1,1,14,1,1,14,1,1,14,1,1,14,1,2,14,0.96756,22,0.03244,2,14,0.59901,22,0.40099,2,14,0.03139,22,0.96861,1,22,1,2,22,0.9824,23,0.0176,2,22,0.94598,23,0.05402,2,22,0.74447,23,0.25553,2,22,0.37675,23,0.62325,1,23,1,1,23,1,1,23,1,1,23,1,1,23,1,1,23,1,2,22,0.00002,23,0.99998,1,23,1,2,22,0.2862,23,0.7138,1,22,1,1,22,1,2,22,0.00491,23,0.99509,2,14,0.00003,22,0.99997,2,14,0.72788,22,0.27212,1,14,1,1,14,1,1,14,1],"userEdges":[],"height":116,"transform":{}}],"name":"Arm right"},{"display":[{"slotPose":[1,0,0,1,0,0],"vertices":[19.82,-276.59,32.95,-294.3,37.05,-306.77,42.62,-326.78,33.93,-328.25,31.14,-334.64,26.39,-333.17,14.74,-353.18,7.36,-355.3,-10.18,-355.3,-19.86,-351.7,-25.27,-339.9,-18.88,-319.73,-10.54,-316.62,-7.54,-318.05,-21.29,-301.38,-22.36,-298.61,-23.24,-290.11,-20.84,-284.23,-20.48,-274.38,-20.74,-269.36,-22.61,-263.04,-25.98,-257.04,-27.21,-251.88,-28.95,-242.72,-29.74,-229.48,-28.9,-217.78,-20.86,-160.53,-23.26,-91.7,-19.73,-74.27,-11.69,-57.91,7.48,-74.4,6.92,-83.99,11.29,-98.66,12.7,-169.02,1.13,-227.22,7.55,-209.09,23.41,-164.02,21.55,-156.28,26.45,-154.32,36.1,-115.13,45.75,-75.95,55.88,-71.27,58.4,-61.89,73,-54.31,80.3,-54.32,84.55,-75.19,79.21,-80.42,85.26,-85.22,85.26,-93.28,82.16,-99.5,81.83,-108.87,71.91,-115.85,56.1,-161.02,59.05,-168.86,50.22,-174.32,43.04,-205.84,35.87,-237.35,24.32,-257.19,17.38,-271.67,-4.75,-231.66,-8.46,-241.91,-8.45,-253.68,-10.09,-262.18,-9.11,-273.85,-8.67,-281.8,-10.09,-285.84,-11.18,-291.72,-9.43,-297.17,-1.7,-304.81,2.77,-312.98,-15.76,-286.05,-1.7,-287.36,13.89,-296.85,10.08,-307.31,-13.03,-301.75,-5.73,-308.18,24.35,-303.72,21.96,-315.59,14.1,-322.79,0.81,-319.52,9.2,-326.49,-5.3,-331.94,-16.21,-234.6,-10.32,-204.35,-5.04,-160.57,-6.06,-86.29,-6.67,-72.28,72.82,-66.8,68.96,-75.53,40.34,-162,26.33,-203.41,15.17,-239.3,7.05,-254.12,4.2,-269.75,9.48,-285.17,57.65,-103.91,1.5,-120.39,-10.76,-123.88,47.2,-123.64],"path":"Layer 37","edges":[25,26,26,27,27,28,28,29,29,30,30,31,31,32,32,33,33,34,34,35,35,36,36,37,37,38,38,39,39,40,40,41,41,42,42,43,43,44,44,45,45,46,46,47,47,48,48,49,49,50,50,51,51,52,52,53,53,54,54,55,55,56,56,57,57,58,58,59,59,0,0,1,1,2,2,3,3,4,4,5,5,6,6,7,7,8,8,9,9,10,10,11,11,12,12,13,13,14,14,15,15,16,16,17,17,18,18,19,19,20,20,21,21,22,22,23,23,24,24,25],"name":"Layer 37","type":"mesh","triangles":[53,99,52,47,48,49,50,47,49,88,45,46,47,88,46,96,89,47,89,88,47,88,44,45,96,47,50,51,52,50,52,96,50,41,42,96,96,42,89,88,43,44,89,43,88,99,96,52,42,43,89,90,39,99,90,99,53,99,40,96,40,41,96,55,53,54,55,90,53,39,40,99,37,90,55,91,37,55,56,91,55,4,2,3,57,91,56,4,78,2,92,91,57,92,36,91,37,39,90,77,1,2,78,77,2,58,92,57,35,36,92,73,0,1,5,6,4,6,78,4,77,73,1,73,95,0,79,78,6,93,92,58,7,81,6,81,79,6,37,38,39,59,93,58,78,74,77,74,73,77,94,93,59,79,74,78,8,81,7,85,98,97,8,82,81,95,59,0,84,85,34,70,74,79,95,94,59,87,30,31,80,70,79,60,35,92,93,61,92,61,60,92,81,80,79,72,95,73,69,72,73,74,69,73,9,82,8,72,94,95,86,32,33,97,86,33,70,69,74,84,27,85,94,63,93,98,28,86,98,86,97,72,65,94,62,61,93,82,80,81,69,68,72,65,64,94,87,31,32,86,87,32,63,62,93,27,98,85,64,63,94,60,84,35,82,14,80,76,69,70,80,14,70,14,76,70,26,84,60,9,10,82,83,26,60,68,67,72,75,68,76,10,11,82,76,68,69,67,66,72,66,65,72,12,13,14,86,29,87,12,14,82,61,83,60,29,30,87,11,12,82,26,27,84,28,29,86,20,63,64,24,83,61,23,24,61,63,22,62,22,23,62,23,61,62,21,22,63,66,71,65,71,19,65,19,20,64,65,19,64,25,26,83,75,67,68,67,71,66,20,21,63,18,19,71,75,16,67,27,28,98,17,71,67,16,17,67,15,16,75,17,18,71,24,25,83,97,33,34,85,97,34,35,84,34,36,37,91,14,75,76,75,15,14],"bonePose":[5,0.30070579950427306,0.9537169507482268,-0.9537169507482268,0.30070579950427306,14.8,-235.75,3,0.10140356989986492,-0.994845372915592,0.994845372915592,0.10140356989986492,-4.34,-236.75,6,0.17106936486110252,-0.9852589874779216,0.9852589874779216,0.17106936486110252,-1.211699868589167,-267.440979754446,11,0.11875057143538374,-0.9929241168305712,0.9929241168305712,0.11875057143538374,1.9188695083690095,-285.471219225292,12,-0.3896062283283517,-0.9209815344770796,0.9209815344770796,-0.3896062283283517,5.197572785699954,-312.885854090984,4,0.07149744433268575,0.997440782930944,-0.997440782930944,0.07149744433268575,-13.06,-225.17,8,0.03280630243612298,0.9994617283920728,-0.9994617283920728,0.03280630243612298,-8.584974959217199,-162.74018139635223,9,-0.13951876123967388,0.9902194278351374,-0.9902194278351374,-0.13951876123967388,-6.3516409202522945,-84.64141047727564,7,0.3263931509994217,0.9452341037968685,-0.9452341037968685,0.3263931509994217,38.38213153806469,-161.5888809946788,10,0.3879982197276907,0.9216601225441744,-0.9216601225441744,0.3879982197276907,67.0006489379911,-76.3199390414089],"uvs":[0.43096,0.2615,0.54505,0.20266,0.5807,0.16125,0.62919,0.09478,0.55361,0.08988,0.52936,0.06863,0.48801,0.07353,0.38676,0.00706,0.32258,0,0.16999,0,0.08585,0.01196,0.03879,0.05119,0.09441,0.11821,0.16693,0.12852,0.19297,0.12376,0.07349,0.17918,0.06414,0.18835,0.05648,0.21662,0.07735,0.23616,0.08049,0.26887,0.07823,0.28554,0.06203,0.30654,0.03264,0.32647,0.02203,0.34361,0.00683,0.37403,0,0.41806,0.00731,0.45694,0.07719,0.64713,0.05635,0.8758,0.087,0.93374,0.15689,0.98808,0.32364,0.93327,0.31873,0.90142,0.35674,0.8527,0.369,0.61895,0.26846,0.42557,0.32427,0.4858,0.46211,0.63552,0.44599,0.66123,0.48864,0.66775,0.57253,0.79792,0.65641,0.9281,0.74456,0.94367,0.76636,0.97482,0.89336,1,0.95687,1,0.99383,0.93064,0.94739,0.91325,1,0.89732,1,0.87052,0.97298,0.84988,0.97014,0.81874,0.88389,0.79556,0.74645,0.64548,0.77204,0.61941,0.69527,0.6013,0.6329,0.4966,0.57052,0.3919,0.47005,0.32599,0.4097,0.27787,0.21729,0.41077,0.18506,0.37673,0.18506,0.33762,0.17085,0.30938,0.17938,0.27063,0.18317,0.24419,0.17085,0.23079,0.16137,0.21124,0.17653,0.19313,0.24383,0.16779,0.28269,0.14063,0.12156,0.23007,0.24383,0.22572,0.37937,0.19422,0.34619,0.15946,0.14526,0.17792,0.20876,0.15656,0.47036,0.17141,0.44951,0.13193,0.38126,0.10803,0.26563,0.1189,0.33861,0.09572,0.21255,0.07762,0.11763,0.40106,0.16882,0.50155,0.21471,0.64701,0.20589,0.89377,0.20059,0.94031,0.8918,0.95852,0.85826,0.92952,0.60936,0.64222,0.48756,0.50464,0.39048,0.38541,0.31987,0.33618,0.29516,0.28425,0.34105,0.233,0.7599,0.83521,0.2716,0.7805,0.16505,0.76889,0.66907,0.76965],"width":115,"weights":[4,5,0.04435,3,0.05959,6,0.57474,11,0.32132,3,6,0.09184,11,0.81246,12,0.0957,3,6,0.01273,11,0.6775,12,0.30976,2,11,0.39606,12,0.60394,2,11,0.32454,12,0.67546,2,11,0.23253,12,0.76747,2,11,0.1841,12,0.8159,2,11,0.00028,12,0.99972,1,12,1,1,12,1,1,12,1,1,12,1,2,11,0.01214,12,0.98786,3,6,0.00138,11,0.10588,12,0.89274,3,6,0.00376,11,0.17386,12,0.82238,3,6,0.23234,11,0.73622,12,0.03144,4,3,0.00067,6,0.27676,11,0.70428,12,0.01829,4,3,0.01551,6,0.43029,11,0.55348,12,0.00073,3,3,0.0634,6,0.55643,11,0.38017,4,4,0.00384,3,0.31614,6,0.57585,11,0.10417,4,4,0.01435,3,0.53237,6,0.41677,11,0.0365,4,4,0.0491,3,0.75925,6,0.18855,11,0.0031,3,4,0.11244,3,0.8214,6,0.06615,3,4,0.18331,3,0.7923,6,0.02439,3,4,0.38325,3,0.61633,6,0.00041,2,4,0.79467,3,0.20533,2,4,0.99237,3,0.00763,2,8,0.62525,4,0.37475,2,9,0.73784,8,0.26216,1,9,1,1,9,1,2,9,0.35618,8,0.64382,1,8,1,1,8,1,2,8,0.3034,4,0.6966,3,4,0.28602,5,0.33806,3,0.37592,3,4,0.00292,5,0.9842,3,0.01289,2,7,0.25992,5,0.74008,2,7,0.62217,5,0.37783,2,7,0.79771,5,0.20229,2,10,0.00851,7,0.99149,2,10,0.8163,7,0.1837,1,10,1,1,10,1,1,10,1,2,10,0.99352,7,0.00648,2,10,0.23526,7,0.76474,2,10,0.044,7,0.956,1,7,1,1,7,1,1,7,1,1,7,1,1,7,1,2,7,0.94469,5,0.05531,2,7,0.83282,5,0.16718,2,7,0.44364,5,0.55636,1,5,1,2,5,0.99411,6,0.00589,4,5,0.55814,3,0.27226,6,0.16941,11,0.0002,4,5,0.10628,3,0.16869,6,0.62131,11,0.10372,3,4,0.25592,5,0.06185,3,0.68222,2,4,0.08044,3,0.91956,3,4,0.02309,3,0.96203,6,0.01488,3,4,0.013,3,0.83855,6,0.14845,4,4,0.00086,3,0.21415,6,0.7415,11,0.0435,3,3,0.04113,6,0.73428,11,0.2246,3,3,0.01995,6,0.57403,11,0.40602,4,3,0.00388,6,0.35352,11,0.63931,12,0.00329,3,6,0.1813,11,0.79649,12,0.0222,3,6,0.01674,11,0.92327,12,0.05999,3,6,0.00068,11,0.45871,12,0.54061,3,3,0.04138,6,0.53941,11,0.41921,2,6,0.39013,11,0.60987,4,5,0.00002,6,0.05089,11,0.93874,12,0.01035,2,11,0.94431,12,0.05569,3,6,0.15058,11,0.78399,12,0.06543,3,6,0.0286,11,0.70724,12,0.26415,3,6,0.02688,11,0.80082,12,0.1723,2,11,0.48496,12,0.51504,2,11,0.15026,12,0.84974,2,6,0.00034,12,0.99966,2,11,0.01927,12,0.98073,1,12,1,2,4,0.51304,3,0.48696,2,4,0.9999,3,0.00009,2,8,0.70975,4,0.29025,1,8,1,2,9,0.96806,8,0.03194,2,10,0.92614,7,0.07386,1,7,1,1,7,1,1,5,1,3,5,0.91307,3,0.07875,6,0.00818,3,5,0.22654,3,0.70096,6,0.0725,4,5,0.03093,3,0.18572,6,0.78135,11,0.002,4,5,0.00486,3,0.00132,6,0.48152,11,0.5123,2,10,0.00333,7,0.99667,1,8,1,2,9,0.00059,8,0.99941,2,10,0.00028,7,0.99972],"userEdges":[],"height":301,"transform":{}}],"name":"Layer 37"},{"display":[{"slotPose":[1,0,0,1,0,0],"vertices":[-46.96,-232.38,-45.54,-255.41,-35.64,-270.15,-32.66,-280.48,-27.61,-287.05,-27.19,-295.25,-22.63,-301.38,-16.8,-305.1,-9.44,-305.3,-4.36,-303.58,-3.73,-297.9,-3.74,-291.87,-7.93,-282.76,-7.71,-275.34,-10.25,-269.76,-14.91,-265.54,-15.45,-259.71,-22.95,-251.03,-29.15,-234.11,-26.79,-229.85,-27.87,-218.14,-32.03,-217.35,-30.54,-210.78,-29.76,-206.27,-27.11,-199.75,-32.74,-200.19,-37.01,-205.28,-41.14,-198.85,-48.78,-193.3,-52.41,-193.3,-48.98,-199.1,-51.63,-202.28,-51.23,-203.66,-53.73,-207.04,-53.14,-209.39,-53.73,-213.36,-50.79,-215.76,-49.27,-218.21,-51.94,-221.53,-51.45,-231.77,-38.56,-232.55,-41.11,-217.31,-44.78,-211.04,-33.81,-209.77,-36.94,-210.56,-20.1,-283.81,-27.13,-266.25,-22.21,-275.61,-34.45,-250.34],"path":"Arm Left","edges":[33,32,32,31,31,30,30,29,29,28,28,27,27,26,26,25,25,24,24,23,23,22,22,21,21,20,20,19,19,18,18,17,17,16,16,15,15,14,14,13,13,12,12,11,11,10,10,9,9,8,8,7,7,6,6,5,5,4,4,3,3,2,2,1,1,0,0,39,39,38,38,37,37,36,36,35,35,34,34,33],"name":"Arm Left","type":"mesh","triangles":[7,6,11,6,45,11,45,12,11,7,11,10,8,7,10,9,8,10,47,14,13,12,45,13,45,47,13,6,5,45,47,15,14,5,4,45,46,16,15,47,46,15,46,17,16,4,3,47,48,18,17,4,47,45,2,46,47,3,2,47,46,48,17,2,1,48,48,40,18,2,48,46,18,40,19,40,21,19,21,20,19,23,25,24,40,41,21,22,43,23,21,43,22,26,25,23,43,26,23,44,43,21,0,40,48,41,44,21,1,0,48,44,26,43,0,41,40,38,37,0,0,37,41,41,42,44,44,42,26,42,27,26,42,32,27,32,30,27,30,28,27,37,42,41,39,38,0,36,34,42,34,32,42,37,36,42,32,31,30,34,33,32,35,34,36,30,29,28],"bonePose":[19,-0.3585308846089625,0.9335178652717444,-0.9335178652717444,-0.3585308846089625,-22.140570117947256,-268.3837369284789,26,-0.27630837585403356,0.9610690305242938,-0.9610690305242938,-0.27630837585403356,-40.90966192722644,-219.5140766815031,17,-0.3013715462069163,0.9535067860990044,-0.9535067860990044,-0.3013715462069163,-13.051204284346658,-297.1415015972249],"uvs":[0.1354,0.6511,0.16382,0.44548,0.36178,0.31379,0.42149,0.22162,0.52243,0.16299,0.53098,0.08973,0.62211,0.03504,0.73873,0.00179,0.88573,0,0.95433,0.0136,1,0.0661,1,0.11991,0.91611,0.20129,0.92051,0.26751,0.86955,0.31738,0.77645,0.35501,0.76567,0.40709,0.61573,0.48453,0.49182,0.63564,0.53886,0.6737,0.5173,0.77826,0.434,0.78526,0.46375,0.84401,0.47943,0.88426,0.53235,0.94245,0.41965,0.93851,0.33439,0.89301,0.25171,0.9504,0.09883,1,0.02631,1,0.09491,0.94822,0.04199,0.91978,0.04983,0.90753,0,0.87734,0.01161,0.85634,0,0.8209,0.05865,0.79947,0.08903,0.77759,0.03582,0.74797,0.04562,0.65653,0.30336,0.64953,0.2524,0.78559,0.1789,0.84159,0.39842,0.85297,0.3357,0.84597,0.67264,0.19197,0.53225,0.34866,0.63053,0.26509,0.38561,0.49073],"width":50,"weights":[2,19,0.98697,26,0.01303,2,17,0.424,19,0.576,2,17,0.09958,19,0.90042,2,17,0.89568,19,0.10432,2,17,0.99741,19,0.00259,1,17,1,1,17,1,1,17,1,1,17,1,1,17,1,1,17,1,1,17,1,1,17,1,2,17,0.99962,19,0.00038,2,17,0.9441,19,0.0559,2,17,0.64158,19,0.35842,2,17,0.176,19,0.824,2,17,0.392,19,0.608,2,17,0.096,19,0.904,1,19,1,2,19,0.87767,26,0.12233,2,19,0.63215,26,0.36785,2,19,0.09575,26,0.90425,2,19,0.01407,26,0.98593,1,26,1,1,26,1,2,19,0.00299,26,0.99701,1,26,1,1,26,1,1,26,1,1,26,1,1,26,1,1,26,1,1,26,1,1,26,1,2,19,0.0017,26,0.9983,2,19,0.05018,26,0.94982,2,19,0.262,26,0.738,2,19,0.61196,26,0.38804,2,19,0.95347,26,0.04653,2,17,0.096,19,0.904,1,26,1,1,26,1,2,19,0.06319,26,0.93681,2,19,0.04454,26,0.95546,1,17,1,2,17,0.1469,19,0.8531,2,17,0.99013,19,0.00987,2,17,0.392,19,0.608],"userEdges":[],"height":112,"transform":{}}],"name":"Arm Left"},{"display":[{"slotPose":[1,0,0,1,0,0],"vertices":[-47.75,-239.24,-41.57,-254.96,-35.38,-270.67,-23.56,-288.05,-18.09,-299.59,4.58,-307.8,27.76,-307.41,38.51,-303.74,50.13,-293.95,61.76,-284.16,77.26,-261.69,70.76,-243.75,64.25,-225.82,49.23,-220.9,34.21,-215.99,14.4,-202.8,7.06,-191.3,2.31,-197.66,-20.05,-205.36,-28.94,-210.12,-39.31,-222.52,10.22,-282.23,-35.05,-239.74,-5.54,-229.61,40.57,-249.8,-16.43,-259.86,40.69,-272.57,16.06,-253.93,27.28,-229.65,33.47,-291.98,-1.49,-242.8,-8.45,-266.35,11.84,-219.8],"path":"Layer 36","edges":[0,20,20,19,19,18,18,17,17,16,16,15,15,14,14,13,13,12,12,11,11,10,10,9,9,8,8,7,7,6,6,5,5,4,4,3,3,2,2,1,1,0],"name":"Layer 36","type":"mesh","triangles":[9,26,10,24,11,10,26,24,10,24,12,11,24,13,12,8,26,9,24,28,13,28,14,13,29,26,8,7,29,8,29,21,26,21,27,26,26,27,24,27,28,24,6,29,7,28,32,14,32,15,14,6,21,29,5,21,6,27,30,28,30,32,28,30,23,32,32,17,15,17,16,15,21,31,27,31,30,27,5,4,21,23,17,32,23,18,17,3,31,21,4,3,21,31,25,30,22,23,30,25,22,30,20,19,23,22,20,23,19,18,23,3,2,25,3,25,31,1,22,25,2,1,25,0,20,22,1,0,22],"bonePose":[21,-0.4694715627858908,0.882947592858927,-0.882947592858927,-0.4694715627858908,-0.7562209809110968,-300.5673087549855,15,0.06488064257826932,0.9978930314510824,-0.9978930314510824,0.06488064257826932,0.06473822593945,-301.0415723743865,18,0.6609190174527773,0.750457228874008,-0.750457228874008,0.6609190174527773,-0.13579946391703285,-301.65986408138815],"uvs":[0,0.59722,0.04943,0.46515,0.09886,0.33308,0.19345,0.18705,0.23713,0.09004,0.41855,0.02107,0.60388,0.02435,0.68999,0.05515,0.78295,0.13743,0.87591,0.21971,1,0.40848,0.94794,0.55924,0.89588,0.70999,0.77576,0.75129,0.65565,0.79258,0.49715,0.90335,0.4385,1,0.40043,0.94661,0.2216,0.88192,0.15047,0.84194,0.06747,0.73772,0.46369,0.23596,0.1016,0.59305,0.33765,0.67817,0.70643,0.50842,0.25051,0.42389,0.70735,0.3171,0.51041,0.47378,0.60019,0.67779,0.64957,0.154,0.37001,0.56733,0.3143,0.36944,0.47674,0.76055],"width":125,"weights":[1,21,1,1,21,1,2,15,0.00022,21,0.99978,3,15,0.00356,21,0.97748,18,0.01896,3,15,0.00094,21,0.88714,18,0.11191,1,18,1,1,18,1,1,18,1,1,18,1,1,18,1,1,18,1,1,18,1,2,15,0.00289,18,0.99711,2,15,0.15545,18,0.84455,2,15,0.56036,18,0.43964,2,15,0.98258,18,0.01742,1,15,1,2,15,0.99149,21,0.00851,2,15,0.61041,21,0.38959,2,15,0.38328,21,0.61672,2,15,0.04709,21,0.95291,2,15,0.34354,18,0.65646,1,21,1,2,15,0.82522,21,0.17478,2,15,0.03445,18,0.96555,2,15,0.14234,21,0.85766,1,18,1,2,15,0.66127,18,0.33873,2,15,0.58656,18,0.41344,1,18,1,2,15,0.91017,21,0.08983,2,15,0.45655,21,0.54345,2,15,0.9553,18,0.0447],"userEdges":[],"height":119,"transform":{}}],"name":"Layer 36"},{"display":[{"slotPose":[1,0,0,1,0,0],"vertices":[6.3,-195.3,-6.92,-216.72,-6.82,-206.83,-31.51,-222.9,-41.41,-238.68,-41.21,-219.37,-54.74,-242.4,-54.74,-276.51,-40.74,-299.12,-19.67,-319.9,-19.09,-344.54,-7.04,-353.3,18.55,-353.3,30.79,-344.34,58.54,-339.26,78.13,-330.44,98.22,-306.92,104.26,-283.89,104.26,-264.88,100.86,-254.49,87.05,-215.58,55.09,-199.51,21.28,-195.3,18.24,-210.5,58.59,-267.96,-40.69,-264.84,-13.09,-269.04,13.84,-323.89],"path":"Layer 35","edges":[6,5,5,4,4,3,3,2,2,1,1,0,0,23,23,22,22,21,21,20,20,19,19,18,18,17,17,16,16,15,15,14,14,13,13,12,12,11,11,10,10,9,9,8,8,7,7,6],"name":"Layer 35","type":"mesh","triangles":[16,24,17,17,24,18,24,19,18,24,20,19,15,24,16,14,24,15,24,21,20,23,21,24,27,24,14,26,23,24,27,26,24,13,27,14,23,22,21,26,1,23,12,27,13,9,26,27,11,27,12,11,10,27,10,9,27,4,3,26,9,8,26,26,3,1,25,4,26,1,3,2,8,25,26,25,6,4,7,25,8,7,6,25,4,6,5,1,0,23],"bonePose":[20,0.0897634727115057,0.9959631112479872,-0.9959631112479872,0.0897634727115057,0.461621996726298,-340.4052376255841,25,-0.2515626323763437,0.9678410210318036,-0.9678410210318036,-0.2515626323763437,-5.953644204504595,-323.0191955352363,24,0.6636651414324586,0.7480297989033823,-0.7480297989033823,0.6636651414324586,6.880959012108247,-335.01971886849606],"uvs":[0.38402,1,0.30081,0.86445,0.30143,0.92709,0.14611,0.82537,0.08386,0.72551,0.08509,0.8477,0,0.70194,0,0.48609,0.08801,0.34293,0.22053,0.21144,0.22423,0.05547,0.30004,0,0.4609,0,0.53795,0.05671,0.71242,0.08881,0.83569,0.14463,0.96204,0.29349,1,0.43925,1,0.55958,0.97868,0.62533,0.89178,0.87159,0.69085,0.97331,0.47821,1,0.4591,0.90385,0.71279,0.54008,0.08841,0.55996,0.26193,0.53335,0.43133,0.18611],"width":159,"weights":[1,20,1,2,25,0.38966,20,0.61034,2,25,0.53849,20,0.46151,2,25,0.9999,20,0.0001,1,25,1,1,25,1,1,25,1,1,25,1,1,25,1,2,25,0.98834,20,0.01166,2,25,0.28126,20,0.71874,3,25,0.07124,20,0.91843,24,0.01033,2,20,0.1974,24,0.8026,2,20,0.00834,24,0.99166,1,24,1,1,24,1,1,24,1,1,24,1,1,24,1,1,24,1,2,20,0.17282,24,0.82718,2,20,0.58928,24,0.41072,2,20,0.89392,24,0.10608,2,20,0.96005,24,0.03995,2,20,0.04524,24,0.95476,1,25,1,2,25,0.80084,20,0.19916,2,20,0.1133,24,0.8867],"userEdges":[],"height":158,"transform":{}}],"name":"Layer 35"},{"display":[{"triangles":[50,21,22,50,22,23,35,50,23,52,23,24,25,52,24,52,35,23,25,39,52,50,20,21,26,39,25,35,19,50,19,20,50,39,35,52,51,39,26,47,19,35,39,47,35,47,18,19,27,51,26,36,47,39,51,36,39,28,51,27,28,44,51,44,36,51,40,18,47,36,40,47,42,44,28,40,17,18,49,40,36,29,42,28,53,36,44,15,16,17,40,15,17,42,53,44,53,38,36,38,49,36,30,42,29,40,13,15,15,13,14,34,13,40,49,34,40,34,12,13,42,37,53,37,48,53,31,42,30,34,45,12,48,38,53,31,37,42,41,49,38,48,41,38,45,11,12,41,34,49,32,37,31,45,10,11,41,46,34,7,9,10,45,7,10,32,33,37,5,45,34,46,5,34,5,6,45,37,43,48,43,41,48,6,7,45,33,43,37,7,8,9,43,2,41,3,46,41,2,3,41,33,0,43,4,5,46,1,2,43,3,4,46,0,1,43],"width":97,"type":"mesh","vertices":[-0.39,21.89,9.94,27.46,20.26,33.03,30.58,38.61,40.91,44.18,51.78,46.78,63.73,48.67,72.54,52.39,90.52,60.52,87.29,49.62,84.05,38.73,78.34,31.59,76.03,28.27,76.24,24.73,78.63,15.97,77.09,14.35,79.28,9.98,76.2,5.67,76.64,0.02,84.79,-9.9,91.57,-12.4,100.43,-16.07,92.37,-32.37,80.06,-39.79,73.49,-45.46,54.42,-43.06,45.18,-39.19,35.94,-35.32,26.7,-31.45,17.47,-27.58,6.78,-24.82,-0.64,-11.81,-4.26,-4.22,-4.2,11.04,54.68,23.86,70.92,-25.2,49.52,-8.22,15.42,1.43,39.26,3.32,57.44,-22.36,64.21,9.11,34.15,21.19,19.16,-12.74,13.05,17.72,36.49,-17.12,68.73,38.59,42.43,34.88,67.2,-9.43,24.25,6.2,48.4,9.87,86.67,-22.63,41.89,-25.6,67.26,-35.2,33.72,-5.74],"transform":{},"uvs":[0,0.17024,0.01115,0.27009,0.0223,0.36994,0.03346,0.46978,0.04461,0.56963,0.08441,0.65932,0.13646,0.75324,0.15483,0.83363,0.18782,1,0.26283,0.92539,0.33785,0.85077,0.36642,0.77631,0.38173,0.74416,0.41337,0.72893,0.50217,0.70439,0.50727,0.68577,0.55728,0.6807,0.57667,0.63839,0.6277,0.6147,0.75936,0.6257,0.81958,0.66208,0.90165,0.70777,0.99555,0.57324,0.98886,0.45055,1,0.37693,0.87047,0.25255,0.78448,0.20516,0.6985,0.15778,0.61251,0.11039,0.52652,0.06301,0.44181,0,0.2877,0.00886,0.20196,0.01901,0.07133,0.09178,0.29765,0.57137,0.81143,0.45455,0.54346,0.38278,0.26589,0.18586,0.38586,0.36437,0.7101,0.37214,0.4787,0.56932,0.20332,0.41267,0.40879,0.14531,0.11254,0.24609,0.54545,0.24787,0.2515,0.74117,0.13308,0.53641,0.6549,0.50282,0.27536,0.27126,0.38184,0.46043,0.87937,0.57886,0.6491,0.24613,0.87631,0.38119,0.4319,0.28208],"path":"Right Cape","edges":[0,1,1,2,2,3,3,4,4,5,5,6,6,7,7,8,8,9,9,10,10,11,11,12,12,13,13,14,14,15,15,16,16,17,17,18,18,19,19,20,20,21,21,22,22,23,23,24,24,25,25,26,26,27,27,28,28,29,29,30,30,31,31,32,32,33,33,0],"userEdges":[],"height":117,"name":"Right Cape"}],"name":"Right Cape"},{"display":[{"slotPose":[1,0,0,1,0,0],"vertices":[-46.96,-232.38,-45.54,-255.41,-35.64,-270.15,-32.66,-280.48,-27.61,-287.05,-27.19,-295.25,-22.63,-301.38,-16.8,-305.1,-9.44,-305.3,-4.36,-303.58,-3.73,-297.9,-3.74,-291.87,-7.93,-282.76,-7.71,-275.34,-10.25,-269.76,-14.91,-265.54,-15.45,-259.71,-22.95,-251.03,-29.15,-234.11,-26.79,-229.85,-27.87,-218.14,-32.03,-217.35,-30.54,-210.78,-29.76,-206.27,-27.11,-199.75,-32.74,-200.19,-37.01,-205.28,-41.14,-198.85,-48.78,-193.3,-52.41,-193.3,-48.98,-199.1,-51.63,-202.28,-51.23,-203.66,-53.73,-207.04,-53.14,-209.39,-53.73,-213.36,-50.79,-215.76,-49.27,-218.21,-51.94,-221.53,-51.45,-231.77,-38.56,-232.55,-41.11,-217.31,-44.78,-211.04,-33.81,-209.77,-36.94,-210.56,-20.1,-283.81,-27.13,-266.25,-22.21,-275.61,-34.45,-250.34],"path":"Arm Left","edges":[33,32,32,31,31,30,30,29,29,28,28,27,27,26,26,25,25,24,24,23,23,22,22,21,21,20,20,19,19,18,18,17,17,16,16,15,15,14,14,13,13,12,12,11,11,10,10,9,9,8,8,7,7,6,6,5,5,4,4,3,3,2,2,1,1,0,0,39,39,38,38,37,37,36,36,35,35,34,34,33],"name":"Arm Left","type":"mesh","triangles":[7,6,11,6,45,11,45,12,11,7,11,10,8,7,10,9,8,10,47,14,13,12,45,13,45,47,13,6,5,45,47,15,14,5,4,45,46,16,15,47,46,15,46,17,16,4,3,47,48,18,17,4,47,45,2,46,47,3,2,47,46,48,17,2,1,48,48,40,18,2,48,46,18,40,19,40,21,19,21,20,19,23,25,24,40,41,21,22,43,23,21,43,22,26,25,23,43,26,23,44,43,21,0,40,48,41,44,21,1,0,48,44,26,43,0,41,40,38,37,0,0,37,41,41,42,44,44,42,26,42,27,26,42,32,27,32,30,27,30,28,27,37,42,41,39,38,0,36,34,42,34,32,42,37,36,42,32,31,30,34,33,32,35,34,36,30,29,28],"bonePose":[19,-0.3585308846089625,0.9335178652717444,-0.9335178652717444,-0.3585308846089625,-22.140570117947256,-268.3837369284789,26,-0.27630837585403356,0.9610690305242938,-0.9610690305242938,-0.27630837585403356,-40.90966192722644,-219.5140766815031,17,-0.3013715462069163,0.9535067860990044,-0.9535067860990044,-0.3013715462069163,-13.051204284346658,-297.1415015972249],"uvs":[0.1354,0.6511,0.16382,0.44548,0.36178,0.31379,0.42149,0.22162,0.52243,0.16299,0.53098,0.08973,0.62211,0.03504,0.73873,0.00179,0.88573,0,0.95433,0.0136,1,0.0661,1,0.11991,0.91611,0.20129,0.92051,0.26751,0.86955,0.31738,0.77645,0.35501,0.76567,0.40709,0.61573,0.48453,0.49182,0.63564,0.53886,0.6737,0.5173,0.77826,0.434,0.78526,0.46375,0.84401,0.47943,0.88426,0.53235,0.94245,0.41965,0.93851,0.33439,0.89301,0.25171,0.9504,0.09883,1,0.02631,1,0.09491,0.94822,0.04199,0.91978,0.04983,0.90753,0,0.87734,0.01161,0.85634,0,0.8209,0.05865,0.79947,0.08903,0.77759,0.03582,0.74797,0.04562,0.65653,0.30336,0.64953,0.2524,0.78559,0.1789,0.84159,0.39842,0.85297,0.3357,0.84597,0.67264,0.19197,0.53225,0.34866,0.63053,0.26509,0.38561,0.49073],"width":50,"weights":[2,19,0.98697,26,0.01303,2,17,0.424,19,0.576,2,17,0.09958,19,0.90042,2,17,0.89568,19,0.10432,2,17,0.99741,19,0.00259,1,17,1,1,17,1,1,17,1,1,17,1,1,17,1,1,17,1,1,17,1,1,17,1,2,17,0.99962,19,0.00038,2,17,0.9441,19,0.0559,2,17,0.64158,19,0.35842,2,17,0.176,19,0.824,2,17,0.392,19,0.608,2,17,0.096,19,0.904,1,19,1,2,19,0.87767,26,0.12233,2,19,0.63215,26,0.36785,2,19,0.09575,26,0.90425,2,19,0.01407,26,0.98593,1,26,1,1,26,1,2,19,0.00299,26,0.99701,1,26,1,1,26,1,1,26,1,1,26,1,1,26,1,1,26,1,1,26,1,1,26,1,2,19,0.0017,26,0.9983,2,19,0.05018,26,0.94982,2,19,0.262,26,0.738,2,19,0.61196,26,0.38804,2,19,0.95347,26,0.04653,2,17,0.096,19,0.904,1,26,1,1,26,1,2,19,0.06319,26,0.93681,2,19,0.04454,26,0.95546,1,17,1,2,17,0.1469,19,0.8531,2,17,0.99013,19,0.00987,2,17,0.392,19,0.608],"userEdges":[],"height":112,"transform":{}}],"name":"Arm LeftOver"},{"display":[{"triangles":[15,16,13,16,12,13,14,15,13,18,29,16,16,29,12,29,11,12,24,10,11,19,24,11,29,19,11,17,18,16,18,19,29,27,8,9,24,9,10,20,24,19,24,26,9,26,27,9,30,26,24,25,7,8,27,25,8,25,6,7,20,30,24,5,6,25,21,30,20,30,28,26,23,25,27,26,28,27,28,23,27,23,2,25,21,28,30,4,5,25,2,3,25,3,4,25,22,23,28,21,22,28,1,2,23,22,1,23,22,0,1],"width":55,"type":"mesh","vertices":[81.67,14.62,80.21,11.83,81.72,8.04,85.14,4.9,88.2,1.63,90.08,-3.09,89.25,-9.5,84.19,-18.26,69.37,-13.38,54.56,-8.5,44.05,-6.82,33.53,-5.15,16.69,-3.2,-0.16,-1.26,-4.02,0.97,-0.77,6.58,7.01,11.11,14.79,15.64,19.7,11.2,30.5,10.74,42.39,15.95,53.8,19.93,71.68,19.99,73.08,9.23,44.06,3.25,79.81,-3.18,59.52,3.3,69.1,-2.99,63.26,9.97,21.49,4.93,52.58,10.46],"transform":{},"uvs":[0.00597,0.78346,0.06324,0.78493,0.10919,0.82222,0.12751,0.87497,0.15119,0.92478,0.20846,0.97118,0.31689,1,0.50093,1,0.55872,0.82244,0.61651,0.64489,0.68571,0.52928,0.7549,0.41368,0.87745,0.23275,1,0.05182,1,0,0.88213,0,0.7401,0.05204,0.59806,0.10408,0.62326,0.17929,0.53234,0.29077,0.34219,0.38014,0.17572,0.47195,0.0123,0.65167,0.16903,0.72827,0.52699,0.47087,0.30314,0.86818,0.38571,0.62626,0.39757,0.75921,0.24667,0.62513,0.70568,0.23377,0.33601,0.51467],"path":"Left Cape","edges":[0,1,1,2,2,3,3,4,4,5,5,6,6,7,7,8,8,9,9,10,10,11,11,12,12,13,13,14,14,15,15,16,16,17,17,18,18,19,19,20,20,21,21,22,22,0],"userEdges":[],"height":86,"name":"Left Cape"}],"name":"Left Cape"}]}]}],"name":"Azrafel","version":"5.0"}