{"width":2048,"height":2048,"name":"OgreOut","imagePath":"OgreOut_tex.png","SubTexture":[{"frameY":-1,"y":1930,"frameWidth":989,"frameX":-1,"frameHeight":118,"width":987,"height":116,"name":"Layer 17","x":1},{"frameY":-1,"y":1,"frameWidth":187,"frameX":-1,"frameHeight":193,"width":185,"height":191,"name":"Layer 16","x":1002},{"frameY":-1,"y":1743,"frameWidth":44,"frameX":-1,"frameHeight":54,"width":42,"height":52,"name":"Layer 15","x":678},{"frameY":-1,"y":869,"frameWidth":220,"frameX":-1,"frameHeight":254,"width":218,"height":252,"name":"Layer 10","x":726},{"frameY":-1,"y":1743,"frameWidth":147,"frameX":-1,"frameHeight":145,"width":145,"height":143,"name":"Layer 12","x":531},{"frameY":-1,"y":1,"frameWidth":357,"frameX":-1,"frameHeight":434,"width":355,"height":432,"name":"Layer 11","x":645},{"frameY":-1,"y":435,"frameWidth":357,"frameX":-1,"frameHeight":434,"width":355,"height":432,"name":"Layer 11 copy 2","x":726},{"width":523,"y":844,"height":649,"name":"Layer 11 copy","x":1},{"width":642,"y":1,"height":841,"name":"Layer 6","x":1},{"frameY":-1,"y":194,"frameWidth":159,"frameX":-1,"frameHeight":62,"width":157,"height":60,"name":"Layer 7","x":1002},{"frameY":-1,"y":1495,"frameWidth":154,"frameX":-1,"frameHeight":79,"width":152,"height":77,"name":"Layer 8","x":372},{"frameY":-1,"y":1646,"frameWidth":165,"frameX":-1,"frameHeight":274,"width":163,"height":272,"name":"Layer 1","x":726},{"frameY":-1,"y":1372,"frameWidth":165,"frameX":-1,"frameHeight":274,"width":163,"height":272,"name":"Layer 1 copy","x":726},{"frameY":-1,"y":1123,"frameWidth":219,"frameX":-1,"frameHeight":249,"width":217,"height":247,"name":"Layer 9","x":726},{"frameY":-1,"y":1743,"frameWidth":159,"frameX":-1,"frameHeight":170,"width":157,"height":168,"name":"Layer 14","x":372},{"frameY":-1,"y":1495,"frameWidth":371,"frameX":-1,"frameHeight":435,"width":369,"height":433,"name":"Layer 4","x":1},{"width":198,"y":869,"height":535,"name":"Layer 13","x":990},{"width":198,"y":844,"height":897,"name":"Layer 13 copy","x":526}]}